Workbook

Sheet INSTRUCTIVO
A1: Autodiagnóstico de sostenibilidad - RAI
A6: El siguiente formato de autodiagnóstico de sostenibilidad tiene como objetivo buscar el grado de implementación de la empresa en los procesos ambientales. Para mas información, por favor consultar la guía de diligenciemiento del Autodiagnostico de Sostenibilidad -RAI
A8: Llene los espacios con las siguientes escalas de aceptación. Marque con una X en el recuadro correspondiente:
B11: Indicador | D11: Símbolo | E11: Escala | F11: Significado
B12: Implementación | D12: IMP | E12: 3 | F12: Una implementación es la realización de una aplicación, instalación o la ejecución de un plan, idea, modelo científico, diseño, especificación, estándar, algoritmo o política.
B13: Mejorable | D13: M | E13: 2 | F13: Hacer pasar una cosa de un estado actual a otro susceptible de mejorar.
B14: Necesita acción | D14: AC | E14: 1 | F14: Realizar otros procesos y/o acciones deferentes a los que se realizan actualmente para mejorar el proceso ambiental.
B15: No aplica/No responde | D15: NA | E15: 0 | F15: No tiene acciones en el proceso y/o no lo conoce.
A18: Interpretación y categorización de sostenibilidad ambiental
A20: Componente ambiental
A22: Aspecto:
A24: A. Económico | C24: A1. Satisfacción de los requerimientos de clientes y mercados
C25: A2. Relación económica con los empleados
C26: A3. Relación económica con proveedores
C27: A4. Satisfacción de los requerimientos de los inversionistas
C28: A5. Relación económica con la sociedad
C29: A6. Relación económica de aspectos financieros
C30: A7. Relación interna de procesos administrativos ambientales
A32: B. Gestión Ambiental | C32: B1. Organización de la gestión ambiental
C33: B2. Protección del medio ambiente a nivel de la producción
C34: B3. Desarrollo de productos tomando en cuenta el medio ambiente
C35: B4. Gestión del recurso hídrico, consumo de agua
C36: B5. Gestión del recurso hídrico (Aguas residuales)
C37: B6. Gestión de residuos sólidos
C38: B7. Gestión del recurso suelo
C39: B8. Emisiones atmosféricas
C40: B9. Legislación, normatividad y ordenanzas
A42: C. Gestión energía | C42: C1. Tipo y clase de energía consumida
C43: C2. Cantidad de Energía Consumida (Identificación por proceso)
C44: C3. Posibilidad de Cambio Tecnológico para Consumo de Energía
A46: D. Gestión de seguridad y salud en el trabajo | C46: D1. Normatividad
C47: D2. Documentación
C48: D3. Comité paritario
C49: D4. Accidentes
C50: D5. Incidentes
C51: D6. Planes de emergencia
C52: D7. Señalización
C53: D8. Elementos de protección personal
C54: D9. Uso de extintores
C55: D10. Panorama de factores de riesgo
A57: E. Aspectos sociales y responsabilidad social empresarial | C57: E1. Empleo y mecanismos de evaluación
C58: E2. Protección de la salud y condiciones laborales
C59: E3. Capacitación, diversidad e incentivos
C60: E4. Transparencia y interacción
C61: E5. Social interno (Se hace mediante encuesta a la cadena de producción de la empresa)
C62: E6. Social externo (Se hace mediante encuesta de producción y servicio de los clientes)
A64: F. Almacenamiento de insumos y materia prima | C64: F1. Registro y fichas de almacenamiento de los insumos y productos
C65: F2. Señalización y rutas de almacenamiento
C66: F3. Insumos con alto riesgo de peligrosidad

Sheet DIAGNOSTICO ECONOMICO
B2: Aspectos ambientales
B4: A. Económico
E6: 3 | G6: 2 | I6: 1 | K6: 0
B8: A1. Satisfacción de los requerimientos de clientes y mercados
B10: 1.- | C10: La empresa dispone de un portafolio de productos/ servicios suficientemente innovadores para mantener o abrir nuevos mercados en el corto, mediano y largo plazo.
F12: IMP | H12: M | J12: AC | L12: NA | M12: =IF(E12="X","",IF(G12="X","",IF(I12="X","",IF(K12="X","","Elegir opción")))) -> Elegir opción | N12: =IF(E12="X",3,IF(G12="X",2,IF(I12="X",1,IF(K12="X",0,"Promedio")))) -> Promedio
B17: 2.- | C17: La empresa continuamente identifica innovaciones para mejorar sus productos y procesos.
F19: IMP | H19: M | J19: AC | L19: NA | M19: =IF(E19="X","",IF(G19="X","",IF(I19="X","",IF(K19="X","","Elegir opción")))) -> Elegir opción | N19: =IF(E19="X",3,IF(G19="X",2,IF(I19="X",1,IF(K19="X",0,"Promedio")))) -> Promedio
B24: 3.- | C24: La empresa continuamente identifica nuevas oportunidades de mercado para sus productos.
F26: IMP | H26: M | J26: AC | L26: NA | M26: =IF(E26="X","",IF(G26="X","",IF(I26="X","",IF(K26="X","","Elegir opción")))) -> Elegir opción | N26: =IF(E26="X",3,IF(G26="X",2,IF(I26="X",1,IF(K26="X",0,"Promedio")))) -> Promedio
B31: 4.- | C31: La empresa siempre entrega el producto/servicio en el tiempo acordado con el cliente.
F33: IMP | H33: M | J33: AC | L33: NA | M33: =IF(E33="X","",IF(G33="X","",IF(I33="X","",IF(K33="X","","Elegir opción")))) -> Elegir opción | N33: =IF(E33="X",3,IF(G33="X",2,IF(I33="X",1,IF(K33="X",0,"Promedio")))) -> Promedio
B38: 5.- | C38: La calidad del producto/ servicio es consistente y de acuerdo a las expectativas del cliente.
F40: IMP | H40: M | J40: AC | L40: NA | M40: =IF(E40="X","",IF(G40="X","",IF(I40="X","",IF(K40="X","","Elegir opción")))) -> Elegir opción | N40: =IF(E40="X",3,IF(G40="X",2,IF(I40="X",1,IF(K40="X",0,"Promedio")))) -> Promedio
B45: 6.- | C45: La empresa recibe un precio que genera un margen de utilidad razonable y sostenible.
F47: IMP | H47: M | J47: AC | L47: NA | M47: =IF(E47="X","",IF(G47="X","",IF(I47="X","",IF(K47="X","","Elegir opción")))) -> Elegir opción | N47: =IF(E47="X",3,IF(G47="X",2,IF(I47="X",1,IF(K47="X",0,"Promedio")))) -> Promedio
B52: 7.- | C52: Las ventas están distribuidas entre varios clientes (no existe dependencia de uno o unos clientes específicos).
F54: IMP | H54: M | J54: AC | L54: NA | M54: =IF(E54="X","",IF(G54="X","",IF(I54="X","",IF(K54="X","","Elegir opción")))) -> Elegir opción | N54: =IF(E54="X",3,IF(G54="X",2,IF(I54="X",1,IF(K54="X",0,"Promedio")))) -> Promedio
B59: 8.- | C59: Las ventas por cliente aumentan cada año.
F61: IMP | H61: M | J61: AC | L61: NA | M61: =IF(E61="X","",IF(G61="X","",IF(I61="X","",IF(K61="X","","Elegir opción")))) -> Elegir opción | N61: =IF(E61="X",3,IF(G61="X",2,IF(I61="X",1,IF(K61="X",0,"Promedio")))) -> Promedio
B67: A2. Relación económica con los empleados
B69: 9.- | C69: Las ventas y utilidades por empleado aumentan cada año.
F71: IMP | H71: M | J71: AC | L71: NA | M71: =IF(E71="X","",IF(G71="X","",IF(I71="X","",IF(K71="X","","Elegir opción")))) -> Elegir opción | N71: =IF(E71="X",3,IF(G71="X",2,IF(I71="X",1,IF(K71="X",0,"Promedio")))) -> Promedio
B76: 10.- | C76: Los empleados reciben un salario y otros incentivos de acuerdo a sus conocimientos, el costo de vida, la cantidad de horas laborales (ej. horas extras) y supera el salario mínimo.
F78: IMP | H78: M | J78: AC | L78: NA | M78: =IF(E78="X","",IF(G78="X","",IF(I78="X","",IF(K78="X","","Elegir opción")))) -> Elegir opción | N78: =IF(E78="X",3,IF(G78="X",2,IF(I78="X",1,IF(K78="X",0,"Promedio")))) -> Promedio
B84: A3. Relación económica con proveedores
B86: 11.- | C86: Los productos, tiempo de entrega, el precio, la calidad y el servicio de los proveedores están de acuerdo a las necesidades de la empresa.
F88: IMP | H88: M | J88: AC | L88: NA | M88: =IF(E88="X","",IF(G88="X","",IF(I88="X","",IF(K88="X","","Elegir opción")))) -> Elegir opción | N88: =IF(E88="X",3,IF(G88="X",2,IF(I88="X",1,IF(K88="X",0,"Promedio")))) -> Promedio
B93: 12.- | C93: La empresa trabaja en conjunto con proveedores para fortalecer relaciones de largo plazo.
F95: IMP | H95: M | J95: AC | L95: NA | M95: =IF(E95="X","",IF(G95="X","",IF(I95="X","",IF(K95="X","","Elegir opción")))) -> Elegir opción | N95: =IF(E95="X",3,IF(G95="X",2,IF(I95="X",1,IF(K95="X",0,"Promedio")))) -> Promedio
B100: 13.- | C100: La disponibilidad de materia prima está garantizada a corto, mediano y largo plazo.
F102: IMP | H102: M | J102: AC | L102: NA | M102: =IF(E102="X","",IF(G102="X","",IF(I102="X","",IF(K102="X","","Elegir opción")))) -> Elegir opción | N102: =IF(E102="X",3,IF(G102="X",2,IF(I102="X",1,IF(K102="X",0,"Promedio")))) -> Promedio
B107: 14.- | C107: Los proveedores reciben un precio de acuerdo a la calidad de los productos y/o servicios que ofrecen y a las condiciones del mercado.
F109: IMP | H109: M | J109: AC | L109: NA | M109: =IF(E109="X","",IF(G109="X","",IF(I109="X","",IF(K109="X","","Elegir opción")))) -> Elegir opción | N109: =IF(E109="X",3,IF(G109="X",2,IF(I109="X",1,IF(K109="X",0,"Promedio")))) -> Promedio
B115: A4. Satisfacción de los requerimientos de los inversionistas
B117: 15.- | C117: La empresa tiene una estructura financiera óptima.
F119: IMP | H119: M | J119: AC | L119: NA | M119: =IF(E119="X","",IF(G119="X","",IF(I119="X","",IF(K119="X","","Elegir opción")))) -> Elegir opción | N119: =IF(E119="X",3,IF(G119="X",2,IF(I119="X",1,IF(K119="X",0,"Promedio")))) -> Promedio
B124: 16.- | C124: La utilidad neta de operación aumenta cada año.
F126: IMP | H126: M | J126: AC | L126: NA | M126: =IF(E126="X","",IF(G126="X","",IF(I126="X","",IF(K126="X","","Elegir opción")))) -> Elegir opción | N126: =IF(E126="X",3,IF(G126="X",2,IF(I126="X",1,IF(K126="X",0,"Promedio")))) -> Promedio
B131: 17.- | C131: La empresa tiene una gestión de cobro adecuada.
F133: IMP | H133: M | J133: AC | L133: NA | M133: =IF(E133="X","",IF(G133="X","",IF(I133="X","",IF(K133="X","","Elegir opción")))) -> Elegir opción | N133: =IF(E133="X",3,IF(G133="X",2,IF(I133="X",1,IF(K133="X",0,"Promedio")))) -> Promedio
B138: 18.- | C138: La empresa tiene un manejo de inventarios adecuado.
F140: IMP | H140: M | J140: AC | L140: NA | M140: =IF(E140="X","",IF(G140="X","",IF(I140="X","",IF(K140="X","","Elegir opción")))) -> Elegir opción | N140: =IF(E140="X",3,IF(G140="X",2,IF(I140="X",1,IF(K140="X",0,"Promedio")))) -> Promedio
B145: 19.- | C145: La utilización de la capacidad instalada es adecuada.
F147: IMP | H147: M | J147: AC | L147: NA | M147: =IF(E147="X","",IF(G147="X","",IF(I147="X","",IF(K147="X","","Elegir opción")))) -> Elegir opción | N147: =IF(E147="X",3,IF(G147="X",2,IF(I147="X",1,IF(K147="X",0,"Promedio")))) -> Promedio
B152: 20.- | C152: La empresa tiene un retorno sobre las inversiones de acuerdo a las condiciones del mercado.
F154: IMP | H154: M | J154: AC | L154: NA | M154: =IF(E154="X","",IF(G154="X","",IF(I154="X","",IF(K154="X","","Elegir opción")))) -> Elegir opción | N154: =IF(E154="X",3,IF(G154="X",2,IF(I154="X",1,IF(K154="X",0,"Promedio")))) -> Promedio
B160: A5. Relación económica con la sociedad
B162: 21.- | C162: La empresa realiza inversiones (tiempo y recursos financieros) en el bienestar familiar de sus empleados y de la comunidad donde se encuentra ubicada.
F164: IMP | H164: M | J164: AC | L164: NA | M164: =IF(E164="X","",IF(G164="X","",IF(I164="X","",IF(K164="X","","Elegir opción")))) -> Elegir opción | N164: =IF(E164="X",3,IF(G164="X",2,IF(I164="X",1,IF(K164="X",0,"Promedio")))) -> Promedio
B169: 22.- | C169: La empresa recibe apoyo de diferentes organizaciones gubernamentales y/o no gubernamentales para lograr sus objetivos económicos, ambientales y sociales.
F171: IMP | H171: M | J171: AC | L171: NA | M171: =IF(E171="X","",IF(G171="X","",IF(I171="X","",IF(K171="X","","Elegir opción")))) -> Elegir opción | N171: =IF(E171="X",3,IF(G171="X",2,IF(I171="X",1,IF(K171="X",0,"Promedio")))) -> Promedio
B177: A6. Relacion económica de aspectos financieros
B179: 23.- | C179: ¿La empresa y/o organización tiene activos suficientes para respaldas los créditos adquiridos en caso de riesgo ambiental?
F181: IMP | H181: M | J181: AC | L181: NA | M181: =IF(E181="X","",IF(G181="X","",IF(I181="X","",IF(K181="X","","Elegir opción")))) -> Elegir opción | N181: =IF(E181="X",3,IF(G181="X",2,IF(I181="X",1,IF(K181="X",0,"Promedio")))) -> Promedio
B186: 24.- | C186: La empresa y/o organización incluyen los aspectos ambientales en los procesos financieros medantes técnicas-económicas-financiero.
F188: IMP | H188: M | J188: AC | L188: NA | M188: =IF(E188="X","",IF(G188="X","",IF(I188="X","",IF(K188="X","","Elegir opción")))) -> Elegir opción | N188: =IF(E188="X",3,IF(G188="X",2,IF(I188="X",1,IF(K188="X",0,"Promedio")))) -> Promedio
B193: 25.- | C193: Tiene en cuenta las variables ambientales dentro de los riesgos financieros de la empresa y/o organización.
F195: IMP | H195: M | J195: AC | L195: NA | M195: =IF(E195="X","",IF(G195="X","",IF(I195="X","",IF(K195="X","","Elegir opción")))) -> Elegir opción | N195: =IF(E195="X",3,IF(G195="X",2,IF(I195="X",1,IF(K195="X",0,"Promedio")))) -> Promedio
B201: A7. Relacion interna de procesos administrativos ambientales
B203: 26.- | C203: Existen controles administrativos ambiental de la empresa y/o organización en el uso racional de los recursos (compara y uso de papel, energía, agua entre otros)
F205: IMP | H205: M | J205: AC | L205: NA | M205: =IF(E205="X","",IF(G205="X","",IF(I205="X","",IF(K205="X","","Elegir opción")))) -> Elegir opción | N205: =IF(E205="X",3,IF(G205="X",2,IF(I205="X",1,IF(K205="X",0,"Promedio")))) -> Promedio

Sheet DATOS A.
B2: Diagnóstico económico
B4: A1. Satisfacción de los requerimientos de clientes y mercados
B5: Item | C5: Diagnóstico promedial
B6: 1 | C6: ='DIAGNOSTICO ECONOMICO'!N12 -> Promedio
B7: 2 | C7: ='DIAGNOSTICO ECONOMICO'!N19 -> Promedio
B8: 3 | C8: ='DIAGNOSTICO ECONOMICO'!N26 -> Promedio
B9: 4 | C9: ='DIAGNOSTICO ECONOMICO'!N33 -> Promedio
B10: 5 | C10: ='DIAGNOSTICO ECONOMICO'!N40 -> Promedio
B11: 6 | C11: ='DIAGNOSTICO ECONOMICO'!N47 -> Promedio
B12: 7 | C12: ='DIAGNOSTICO ECONOMICO'!N54 -> Promedio
B13: 8 | C13: ='DIAGNOSTICO ECONOMICO'!N61 -> Promedio
B15: A2. Relación económica con los empleados
B16: 9 | C16: ='DIAGNOSTICO ECONOMICO'!N71 -> Promedio
B17: 10 | C17: ='DIAGNOSTICO ECONOMICO'!N78 -> Promedio | H17: Promedio
G18: A1 | H18: =SUMIF(C6:C13,">0",C6:C13)/COUNTIF(C6:C13,">0") -> #DIV/0!
B19: A3. Relación económica con proveedores | G19: A2 | H19: =SUMIF(C16:C17,">0",C16:C17)/COUNTIF(C16:C17,">0") -> #DIV/0!
B20: 11 | C20: ='DIAGNOSTICO ECONOMICO'!N88 -> Promedio | G20: A3 | H20: =SUMIF(C20:C23,">0",C20:C23)/COUNTIF(C20:C23,">0") -> #DIV/0!
B21: 12 | C21: ='DIAGNOSTICO ECONOMICO'!N95 -> Promedio | G21: A4 | H21: =SUMIF(C26:C31,">0",C26:C31)/COUNTIF(C26:C31,">0") -> #DIV/0!
B22: 13 | C22: ='DIAGNOSTICO ECONOMICO'!N102 -> Promedio | G22: A5 | H22: =SUMIF(C34:C35,">0",C34:C35)/COUNTIF(C34:C35,">0") -> #DIV/0!
B23: 14 | C23: ='DIAGNOSTICO ECONOMICO'!N109 -> Promedio | G23: A6 | H23: =SUMIF(C38:C40,">0",C38:C40)/COUNTIF(C38:C40,">0") -> #DIV/0!
G24: A7 | H24: =SUMIF(C43,">0",C43)/COUNTIF(C43,">0") -> #DIV/0!
B25: A4. Satisfacción de los requerimientos de los inversionistas
B26: 15 | C26: ='DIAGNOSTICO ECONOMICO'!N119 -> Promedio | G26: Diagnostico económico | H26: =((SUM(H18:H25)/7)*100)/7 -> #DIV/0!
B27: 16 | C27: ='DIAGNOSTICO ECONOMICO'!N126 -> Promedio
B28: 17 | C28: ='DIAGNOSTICO ECONOMICO'!N133 -> Promedio
B29: 18 | C29: ='DIAGNOSTICO ECONOMICO'!N140 -> Promedio
B30: 19 | C30: ='DIAGNOSTICO ECONOMICO'!N147 -> Promedio
B31: 20 | C31: ='DIAGNOSTICO ECONOMICO'!N154 -> Promedio
B33: A5. Relación económica con la sociedad
B34: 21 | C34: ='DIAGNOSTICO ECONOMICO'!N164 -> Promedio
B35: 22 | C35: ='DIAGNOSTICO ECONOMICO'!N171 -> Promedio
B37: A6. Relación económica de aspectos financieros
B38: 23 | C38: ='DIAGNOSTICO ECONOMICO'!N181 -> Promedio
B39: 24 | C39: ='DIAGNOSTICO ECONOMICO'!N188 -> Promedio
B40: 25 | C40: ='DIAGNOSTICO ECONOMICO'!N195 -> Promedio
B42: A7. Relación interna de procesos administrativos ambientales
B43: 26 | C43: ='DIAGNOSTICO ECONOMICO'!N205 -> Promedio

Sheet DIAGNOSTICO GESTIÓN AMBIENTAL
B2: Aspectos ambientales
B4: B. Medio ambiental
E6: 3 | G6: 2 | I6: 1 | K6: 0
B8: B1. Organización de la gestión ambiental
B10: 27.- | C10: La protección del medio ambiente es un objetivo empresarial importante y cuenta con el apoyo activo de la alta gerencia.
F12: IMP | H12: M | J12: AC | L12: NA | M12: =IF(E12="X","",IF(G12="X","",IF(I12="X","",IF(K12="X","","Elegir opción")))) -> Elegir opción | N12: =IF(E12="X",3,IF(G12="X",2,IF(I12="X",1,IF(K12="X",0,"Promedio")))) -> Promedio
B17: 28.- | C17: La empresa ha definido e implementado planes para mejorar su impacto ambiental.
F19: IMP | H19: M | J19: AC | L19: NA | M19: =IF(E19="X","",IF(G19="X","",IF(I19="X","",IF(K19="X","","Elegir opción")))) -> Elegir opción | N19: =IF(E19="X",3,IF(G19="X",2,IF(I19="X",1,IF(K19="X",0,"Promedio")))) -> Promedio
B24: 29.- | C24: Se mantiene un registro del consumo y salidas de materiales de mayor relevancia y de energía.
F26: IMP | H26: M | J26: AC | L26: NA | M26: =IF(E26="X","",IF(G26="X","",IF(I26="X","",IF(K26="X","","Elegir opción")))) -> Elegir opción | N26: =IF(E26="X",3,IF(G26="X",2,IF(I26="X",1,IF(K26="X",0,"Promedio")))) -> Promedio
B31: 30.- | C31: Antes de hacer grandes inversiones (Por ejemplo, en nuevas instalaciones, maquinaria o equipos) se investiga el impacto de las mismas en el medio ambiente.
F33: IMP | H33: M | J33: AC | L33: NA | M33: =IF(E33="X","",IF(G33="X","",IF(I33="X","",IF(K33="X","","Elegir opción")))) -> Elegir opción | N33: =IF(E33="X",3,IF(G33="X",2,IF(I33="X",1,IF(K33="X",0,"Promedio")))) -> Promedio
B38: 31.- | C38: En la empresa se ha logrado asegurar un apoyo amplio para la gestión ambiental a través de grupos de discusión y estructuras establecidas.
F40: IMP | H40: M | J40: AC | L40: NA | M40: =IF(E40="X","",IF(G40="X","",IF(I40="X","",IF(K40="X","","Elegir opción")))) -> Elegir opción | N40: =IF(E40="X",3,IF(G40="X",2,IF(I40="X",1,IF(K40="X",0,"Promedio")))) -> Promedio
B46: B2. Protección del medio ambiente a nivel de la producción
B48: 32.- | C48: En la empresa se trata de minimizar el uso de recursos (por ejemplo, materiales, energía, agua, etc.).
F50: IMP | H50: M | J50: AC | L50: NA | M50: =IF(E50="X","",IF(G50="X","",IF(I50="X","",IF(K50="X","","Elegir opción")))) -> Elegir opción | N50: =IF(E50="X",3,IF(G50="X",2,IF(I50="X",1,IF(K50="X",0,"Promedio")))) -> Promedio
B55: 33.- | C55: Hasta donde sea posible, en la empresa se utiliza energía limpia (generada a través de la energía eólica, energía solar, gas y/o la cogeneración).
F57: IMP | H57: M | J57: AC | L57: NA | M57: =IF(E57="X","",IF(G57="X","",IF(I57="X","",IF(K57="X","","Elegir opción")))) -> Elegir opción | N57: =IF(E57="X",3,IF(G57="X",2,IF(I57="X",1,IF(K57="X",0,"Promedio")))) -> Promedio
B62: 34.- | C62: Se están tomando medidas concretas para reducir las emisiones al aire (sustancias como dióxido de carbono, dióxido de azufre y óxidos de nitrógeno).
F64: IMP | H64: M | J64: AC | L64: NA | M64: =IF(E64="X","",IF(G64="X","",IF(I64="X","",IF(K64="X","","Elegir opción")))) -> Elegir opción | N64: =IF(E64="X",3,IF(G64="X",2,IF(I64="X",1,IF(K64="X",0,"Promedio")))) -> Promedio
B69: 35.- | C69: Se están tomando medidas concretas para reducir la cantidad de desechos sólidos, líquidos y gaseosos.
F71: IMP | H71: M | J71: AC | L71: NA | M71: =IF(E71="X","",IF(G71="X","",IF(I71="X","",IF(K71="X","","Elegir opción")))) -> Elegir opción | N71: =IF(E71="X",3,IF(G71="X",2,IF(I71="X",1,IF(K71="X",0,"Promedio")))) -> Promedio
B76: 36.- | C76: La empresa trata de evitar la generación de desechos tóxicos.
F78: IMP | H78: M | J78: AC | L78: NA | M78: =IF(E78="X","",IF(G78="X","",IF(I78="X","",IF(K78="X","","Elegir opción")))) -> Elegir opción | N78: =IF(E78="X",3,IF(G78="X",2,IF(I78="X",1,IF(K78="X",0,"Promedio")))) -> Promedio
B83: 37.- | C83: La empresa trata de evitar la generación de aguas residuales.
F85: IMP | H85: M | J85: AC | L85: NA | M85: =IF(E85="X","",IF(G85="X","",IF(I85="X","",IF(K85="X","","Elegir opción")))) -> Elegir opción | N85: =IF(E85="X",3,IF(G85="X",2,IF(I85="X",1,IF(K85="X",0,"Promedio")))) -> Promedio
B90: 38.- | C90: La empresa trata de optimizar el transporte de materiales, productos intermedios y productos terminados.
F92: IMP | H92: M | J92: AC | L92: NA | M92: =IF(E92="X","",IF(G92="X","",IF(I92="X","",IF(K92="X","","Elegir opción")))) -> Elegir opción | N92: =IF(E92="X",3,IF(G92="X",2,IF(I92="X",1,IF(K92="X",0,"Promedio")))) -> Promedio
B97: 39- | C97: La empresa evita hacer negocios con proveedores que no toman en cuenta consideraciones ambientales o que no cumplen las normas ambientales.
F99: IMP | H99: M | J99: AC | L99: NA | M99: =IF(E99="X","",IF(G99="X","",IF(I99="X","",IF(K99="X","","Elegir opción")))) -> Elegir opción | N99: =IF(E99="X",3,IF(G99="X",2,IF(I99="X",1,IF(K99="X",0,"Promedio")))) -> Promedio
B105: B3. Desarrollo de productos tomando en cuenta el medio ambiente
B107: 40.- | C107: En el diseño de productos la empresa procura minimizar el uso de materia prima e incluye criterios ecológicos al seleccionarlas.
F109: IMP | H109: M | J109: AC | L109: NA | M109: =IF(E109="X","",IF(G109="X","",IF(I109="X","",IF(K109="X","","Elegir opción")))) -> Elegir opción | N109: =IF(E109="X",3,IF(G109="X",2,IF(I109="X",1,IF(K109="X",0,"Promedio")))) -> Promedio
B114: 41.- | C114: En el diseño de productos la empresa procura minimizar el uso de materiales de empaque e incluye criterios ecológicos al seleccionarlos.
F116: IMP | H116: M | J116: AC | L116: NA | M116: =IF(E116="X","",IF(G116="X","",IF(I116="X","",IF(K116="X","","Elegir opción")))) -> Elegir opción | N116: =IF(E116="X",3,IF(G116="X",2,IF(I116="X",1,IF(K116="X",0,"Promedio")))) -> Promedio
B121: 42.- | C121: En el diseño de productos la empresa toma en cuenta aspectos ambientales al definir el proceso para su producción (uso energía, desechos, agua residuales, etc.).
F123: IMP | H123: M | J123: AC | L123: NA | M123: =IF(E123="X","",IF(G123="X","",IF(I123="X","",IF(K123="X","","Elegir opción")))) -> Elegir opción | N123: =IF(E123="X",3,IF(G123="X",2,IF(I123="X",1,IF(K123="X",0,"Promedio")))) -> Promedio
B128: 43.- | C128: En la empresa se procura diseñar productos que requieran un mínimo de recursos y de energía durante su utilización o consumo.
F130: IMP | H130: M | J130: AC | L130: NA | M130: =IF(E130="X","",IF(G130="X","",IF(I130="X","",IF(K130="X","","Elegir opción")))) -> Elegir opción | N130: =IF(E130="X",3,IF(G130="X",2,IF(I130="X",1,IF(K130="X",0,"Promedio")))) -> Promedio
B135: 44.- | C135: En la empresa se fomenta el aprovechamiento de los productos al final de su vida útil (por ejemplo, mediante reutilización, procesamiento o reciclaje).
F137: IMP | H137: M | J137: AC | L137: NA | M137: =IF(E137="X","",IF(G137="X","",IF(I137="X","",IF(K137="X","","Elegir opción")))) -> Elegir opción | N137: =IF(E137="X",3,IF(G137="X",2,IF(I137="X",1,IF(K137="X",0,"Promedio")))) -> Promedio
B143: B4. Gestión del recurso hídrico, consumo de agua
B145: 45.- | C145: ¿Se tiene identificada la fuente de agua para consumo humano?
F147: IMP | H147: M | J147: AC | L147: NA | M147: =IF(E147="X","",IF(G147="X","",IF(I147="X","",IF(K147="X","","Elegir opción")))) -> Elegir opción | N147: =IF(E147="X",3,IF(G147="X",2,IF(I147="X",1,IF(K147="X",0,"Promedio")))) -> Promedio
B152: 46.- | C152: ¿Se utiliza el agua lluvia en algún proceso?
F154: IMP | H154: M | J154: AC | L154: NA | M154: =IF(E154="X","",IF(G154="X","",IF(I154="X","",IF(K154="X","","Elegir opción")))) -> Elegir opción | N154: =IF(E154="X",3,IF(G154="X",2,IF(I154="X",1,IF(K154="X",0,"Promedio")))) -> Promedio
B159: 47.- | C159: ¿Se utilizan las aguas subterráneas?
F161: IMP | H161: M | J161: AC | L161: NA | M161: =IF(E161="X","",IF(G161="X","",IF(I161="X","",IF(K161="X","","Elegir opción")))) -> Elegir opción | N161: =IF(E161="X",3,IF(G161="X",2,IF(I161="X",1,IF(K161="X",0,"Promedio")))) -> Promedio
B166: 48.- | C166: ¿Se utiliza agua almacenada en tanques?
F168: IMP | H168: M | J168: AC | L168: NA | M168: =IF(E168="X","",IF(G168="X","",IF(I168="X","",IF(K168="X","","Elegir opción")))) -> Elegir opción | N168: =IF(E168="X",3,IF(G168="X",2,IF(I168="X",1,IF(K168="X",0,"Promedio")))) -> Promedio
B173: 49.- | C173: ¿Se tiene tratamiento de purificación para el agua almacenada en tanques?
F175: IMP | H175: M | J175: AC | L175: NA | M175: =IF(E175="X","",IF(G175="X","",IF(I175="X","",IF(K175="X","","Elegir opción")))) -> Elegir opción | N175: =IF(E175="X",3,IF(G175="X",2,IF(I175="X",1,IF(K175="X",0,"Promedio")))) -> Promedio
B180: 50.- | C180: ¿Tiene identificados los procesos en que utiliza agua cruda?
F182: IMP | H182: M | J182: AC | L182: NA | M182: =IF(E182="X","",IF(G182="X","",IF(I182="X","",IF(K182="X","","Elegir opción")))) -> Elegir opción | N182: =IF(E182="X",3,IF(G182="X",2,IF(I182="X",1,IF(K182="X",0,"Promedio")))) -> Promedio
B187: 51.- | C187: ¿Tiene identificados los procesos en que utiliza agua potable?
F189: IMP | H189: M | J189: AC | L189: NA | M189: =IF(E189="X","",IF(G189="X","",IF(I189="X","",IF(K189="X","","Elegir opción")))) -> Elegir opción | N189: =IF(E189="X",3,IF(G189="X",2,IF(I189="X",1,IF(K189="X",0,"Promedio")))) -> Promedio
B194: 52.- | C194: ¿Tiene identificados los procesos en que utiliza agua tratada?
F196: IMP | H196: M | J196: AC | L196: NA | M196: =IF(E196="X","",IF(G196="X","",IF(I196="X","",IF(K196="X","","Elegir opción")))) -> Elegir opción | N196: =IF(E196="X",3,IF(G196="X",2,IF(I196="X",1,IF(K196="X",0,"Promedio")))) -> Promedio
B201: 53.- | C201: ¿Se hacen pruebas de laboratorio al agua de consumo?
F203: IMP | H203: M | J203: AC | L203: NA | M203: =IF(E203="X","",IF(G203="X","",IF(I203="X","",IF(K203="X","","Elegir opción")))) -> Elegir opción | N203: =IF(E203="X",3,IF(G203="X",2,IF(I203="X",1,IF(K203="X",0,"Promedio")))) -> Promedio
B208: 54.- | C208: ¿El agua de consumo recibe tratamiento?
F210: IMP | H210: M | J210: AC | L210: NA | M210: =IF(E210="X","",IF(G210="X","",IF(I210="X","",IF(K210="X","","Elegir opción")))) -> Elegir opción | N210: =IF(E210="X",3,IF(G210="X",2,IF(I210="X",1,IF(K210="X",0,"Promedio")))) -> Promedio
B215: 55.- | C215: ¿Se han reportado casos de afección a la salud humana por la falta de tratamiento de aguas?
F217: IMP | H217: M | J217: AC | L217: NA | M217: =IF(E217="X","",IF(G217="X","",IF(I217="X","",IF(K217="X","","Elegir opción")))) -> Elegir opción | N217: =IF(E217="X",3,IF(G217="X",2,IF(I217="X",1,IF(K217="X",0,"Promedio")))) -> Promedio
B222: 56.- | C222: ¿Se tienen cuantificados los costos anuales del tratamiento de aguas?
F224: IMP | H224: M | J224: AC | L224: NA | M224: =IF(E224="X","",IF(G224="X","",IF(I224="X","",IF(K224="X","","Elegir opción")))) -> Elegir opción | N224: =IF(E224="X",3,IF(G224="X",2,IF(I224="X",1,IF(K224="X",0,"Promedio")))) -> Promedio
B231: B5. Gestión del recurso hídrico (Aguas residuales)
B233: 57.- | C233: ¿Se conoce donde se vierten las aguas residuales?
F235: IMP | H235: M | J235: AC | L235: NA | M235: =IF(E235="X","",IF(G235="X","",IF(I235="X","",IF(K235="X","","Elegir opción")))) -> Elegir opción | N235: =IF(E235="X",3,IF(G235="X",2,IF(I235="X",1,IF(K235="X",0,"Promedio")))) -> Promedio
B240: 58.- | C240: ¿Existe tratamiento de las aguas residuales?
F242: IMP | H242: M | J242: AC | L242: NA | M242: =IF(E242="X","",IF(G242="X","",IF(I242="X","",IF(K242="X","","Elegir opción")))) -> Elegir opción | N242: =IF(E242="X",3,IF(G242="X",2,IF(I242="X",1,IF(K242="X",0,"Promedio")))) -> Promedio
B247: 59.- | C247: ¿Se conoce el tipo de tratamiento que se hace a las aguas residuales?
F249: IMP | H249: M | J249: AC | L249: NA | M249: =IF(E249="X","",IF(G249="X","",IF(I249="X","",IF(K249="X","","Elegir opción")))) -> Elegir opción | N249: =IF(E249="X",3,IF(G249="X",2,IF(I249="X",1,IF(K249="X",0,"Promedio")))) -> Promedio
B254: 60.- | C254: ¿Se tiene registro de los costos por tratamiento de las aguas residuales?
F256: IMP | H256: M | J256: AC | L256: NA | M256: =IF(E256="X","",IF(G256="X","",IF(I256="X","",IF(K256="X","","Elegir opción")))) -> Elegir opción | N256: =IF(E256="X",3,IF(G256="X",2,IF(I256="X",1,IF(K256="X",0,"Promedio")))) -> Promedio
B261: 61.- | C261: ¿Se conoce y se aplica la legislación relacionada con el manejo de las aguas residuales?
F263: IMP | H263: M | J263: AC | L263: NA | M263: =IF(E263="X","",IF(G263="X","",IF(I263="X","",IF(K263="X","","Elegir opción")))) -> Elegir opción | N263: =IF(E263="X",3,IF(G263="X",2,IF(I263="X",1,IF(K263="X",0,"Promedio")))) -> Promedio
B268: 62.- | C268: ¿Existen indicadores de aguas residuales?
F270: IMP | H270: M | J270: AC | L270: NA | M270: =IF(E270="X","",IF(G270="X","",IF(I270="X","",IF(K270="X","","Elegir opción")))) -> Elegir opción | N270: =IF(E270="X",3,IF(G270="X",2,IF(I270="X",1,IF(K270="X",0,"Promedio")))) -> Promedio
B275: 63.- | C275: ¿Existen mediciones de los parámetros físicos y químicos de las aguas residuales? (Si la respuesta es afirmativa, anexe los registros)
F277: IMP | H277: M | J277: AC | L277: NA | M277: =IF(E277="X","",IF(G277="X","",IF(I277="X","",IF(K277="X","","Elegir opción")))) -> Elegir opción | N277: =IF(E277="X",3,IF(G277="X",2,IF(I277="X",1,IF(K277="X",0,"Promedio")))) -> Promedio
B282: 64.- | C282: Reducción del consumo de agua en el proceso productivo
F284: IMP | H284: M | J284: AC | L284: NA | M284: =IF(E284="X","",IF(G284="X","",IF(I284="X","",IF(K284="X","","Elegir opción")))) -> Elegir opción | N284: =IF(E284="X",3,IF(G284="X",2,IF(I284="X",1,IF(K284="X",0,"Promedio")))) -> Promedio
B289: 65.- | C289: ¿Se han adecuado equipos para mejorar el rendimiento en el consumo de agua?
F291: IMP | H291: M | J291: AC | L291: NA | M291: =IF(E291="X","",IF(G291="X","",IF(I291="X","",IF(K291="X","","Elegir opción")))) -> Elegir opción | N291: =IF(E291="X",3,IF(G291="X",2,IF(I291="X",1,IF(K291="X",0,"Promedio")))) -> Promedio
B296: 66.- | C296: ¿Se han ejecutado acciones para reducir el consumo de agua?
F298: IMP | H298: M | J298: AC | L298: NA | M298: =IF(E298="X","",IF(G298="X","",IF(I298="X","",IF(K298="X","","Elegir opción")))) -> Elegir opción | N298: =IF(E298="X",3,IF(G298="X",2,IF(I298="X",1,IF(K298="X",0,"Promedio")))) -> Promedio
B303: 67.- | C303: ¿Existe consumo excesivo de agua en los procesos de producción?
F305: IMP | H305: M | J305: AC | L305: NA | M305: =IF(E305="X","",IF(G305="X","",IF(I305="X","",IF(K305="X","","Elegir opción")))) -> Elegir opción | N305: =IF(E305="X",3,IF(G305="X",2,IF(I305="X",1,IF(K305="X",0,"Promedio")))) -> Promedio
B310: 68.- | C310: ¿Se han ejecutado planes de capacitación para mejorar las prácticas de manejo de aguas?
F312: IMP | H312: M | J312: AC | L312: NA | M312: =IF(E312="X","",IF(G312="X","",IF(I312="X","",IF(K312="X","","Elegir opción")))) -> Elegir opción | N312: =IF(E312="X",3,IF(G312="X",2,IF(I312="X",1,IF(K312="X",0,"Promedio")))) -> Promedio
B317: 69.- | C317: Evitar derrames y excesos para optimizar el consumo de agua
F319: IMP | H319: M | J319: AC | L319: NA | M319: =IF(E319="X","",IF(G319="X","",IF(I319="X","",IF(K319="X","","Elegir opción")))) -> Elegir opción | N319: =IF(E319="X",3,IF(G319="X",2,IF(I319="X",1,IF(K319="X",0,"Promedio")))) -> Promedio
B324: 70.- | C324: ¿Se regulan las bombas de agua y las cañerías?
F326: IMP | H326: M | J326: AC | L326: NA | M326: =IF(E326="X","",IF(G326="X","",IF(I326="X","",IF(K326="X","","Elegir opción")))) -> Elegir opción | N326: =IF(E326="X",3,IF(G326="X",2,IF(I326="X",1,IF(K326="X",0,"Promedio")))) -> Promedio
B331: 71.- | C331: ¿Tiene instalados instrumentos para la medición del agua?
F333: IMP | H333: M | J333: AC | L333: NA | M333: =IF(E333="X","",IF(G333="X","",IF(I333="X","",IF(K333="X","","Elegir opción")))) -> Elegir opción | N333: =IF(E333="X",3,IF(G333="X",2,IF(I333="X",1,IF(K333="X",0,"Promedio")))) -> Promedio
B338: 72.- | C338: Fugas que causan goteo
F340: IMP | H340: M | J340: AC | L340: NA | M340: =IF(E340="X","",IF(G340="X","",IF(I340="X","",IF(K340="X","","Elegir opción")))) -> Elegir opción | N340: =IF(E340="X",3,IF(G340="X",2,IF(I340="X",1,IF(K340="X",0,"Promedio")))) -> Promedio
...

Sheet DATOS B.
B2: Diagnóstico ambiental
B4: B1. Organización de la gestión ambiental
B5: Item | C5: Diagnóstico promedial
B6: 27 | C6: ='DIAGNOSTICO GESTIÓN AMBIENTAL'!N12 -> Promedio
B7: 28 | C7: ='DIAGNOSTICO GESTIÓN AMBIENTAL'!N19 -> Promedio
B8: 29 | C8: ='DIAGNOSTICO GESTIÓN AMBIENTAL'!N26 -> Promedio
B9: 30 | C9: ='DIAGNOSTICO GESTIÓN AMBIENTAL'!N33 -> Promedio
B10: 31 | C10: ='DIAGNOSTICO GESTIÓN AMBIENTAL'!N40 -> Promedio | G10: B1 | H10: =SUMIF(C6:C10,">0",C6:C10)/COUNTIF(C6:C10,">0") -> #DIV/0!
G11: B2 | H11: =SUMIF(C13:C20,">0",C13:C20)/COUNTIF(C13:C20,">0") -> #DIV/0!
B12: B2. Protección del medio ambiente a nivel de la producción | G12: B3 | H12: =SUMIF(C23:C27,">0",C23:C27)/COUNTIF(C23:C27,">0") -> #DIV/0!
B13: 32 | C13: ='DIAGNOSTICO GESTIÓN AMBIENTAL'!N50 -> Promedio | G13: B4 | H13: =SUMIF(C30:C41,">0",C30:C41)/COUNTIF(C30:C41,">0") -> #DIV/0!
B14: 33 | C14: ='DIAGNOSTICO GESTIÓN AMBIENTAL'!N57 -> Promedio | G14: B5 | H14: =SUMIF(C44:C78,">0",C44:C78)/COUNTIF(C44:C78,">0") -> #DIV/0!
B15: 34 | C15: ='DIAGNOSTICO GESTIÓN AMBIENTAL'!N64 -> Promedio | G15: B6 | H15: =SUMIF(C81:C92,">0",C81:C92)/COUNTIF(C81:C92,">0") -> #DIV/0!
B16: 35 | C16: ='DIAGNOSTICO GESTIÓN AMBIENTAL'!N71 -> Promedio
B17: 36 | C17: ='DIAGNOSTICO GESTIÓN AMBIENTAL'!N78 -> Promedio | G17: Diagnóstico ambiental | H17: =((SUM(H10:H16)/6)*100)/6 -> #DIV/0!
B18: 37 | C18: ='DIAGNOSTICO GESTIÓN AMBIENTAL'!N85 -> Promedio
B19: 38 | C19: ='DIAGNOSTICO GESTIÓN AMBIENTAL'!N92 -> Promedio
B20: 39 | C20: ='DIAGNOSTICO GESTIÓN AMBIENTAL'!N99 -> Promedio
B22: B3. Desarrollo de productos tomando en cuenta el medio ambiente
B23: 40 | C23: ='DIAGNOSTICO GESTIÓN AMBIENTAL'!N109 -> Promedio
B24: 41 | C24: ='DIAGNOSTICO GESTIÓN AMBIENTAL'!N116 -> Promedio
B25: 42 | C25: ='DIAGNOSTICO GESTIÓN AMBIENTAL'!N123 -> Promedio
B26: 43 | C26: ='DIAGNOSTICO GESTIÓN AMBIENTAL'!N130 -> Promedio
B27: 44 | C27: ='DIAGNOSTICO GESTIÓN AMBIENTAL'!N137 -> Promedio
B29: B4. Gestión del recurso hídrico, consumo de agua
B30: 45 | C30: ='DIAGNOSTICO GESTIÓN AMBIENTAL'!N147 -> Promedio
B31: 46 | C31: ='DIAGNOSTICO GESTIÓN AMBIENTAL'!N154 -> Promedio
B32: 47 | C32: ='DIAGNOSTICO GESTIÓN AMBIENTAL'!N161 -> Promedio
B33: 48 | C33: ='DIAGNOSTICO GESTIÓN AMBIENTAL'!N168 -> Promedio
B34: 49 | C34: ='DIAGNOSTICO GESTIÓN AMBIENTAL'!N175 -> Promedio
B35: 50 | C35: ='DIAGNOSTICO GESTIÓN AMBIENTAL'!N182 -> Promedio
B36: 51 | C36: ='DIAGNOSTICO GESTIÓN AMBIENTAL'!N189 -> Promedio
B37: 52 | C37: ='DIAGNOSTICO GESTIÓN AMBIENTAL'!N196 -> Promedio
B38: 53 | C38: ='DIAGNOSTICO GESTIÓN AMBIENTAL'!N203 -> Promedio
B39: 54 | C39: ='DIAGNOSTICO GESTIÓN AMBIENTAL'!N210 -> Promedio
B40: 55 | C40: ='DIAGNOSTICO GESTIÓN AMBIENTAL'!N217 -> Promedio
B41: 56 | C41: ='DIAGNOSTICO GESTIÓN AMBIENTAL'!N224 -> Promedio
B43: B5. Gestión del Recurso Hídrico (Aguas Residuales)
B44: 57 | C44: ='DIAGNOSTICO GESTIÓN AMBIENTAL'!N235 -> Promedio
B45: 58 | C45: ='DIAGNOSTICO GESTIÓN AMBIENTAL'!N242 -> Promedio
B46: 59 | C46: ='DIAGNOSTICO GESTIÓN AMBIENTAL'!N249 -> Promedio
B47: 60 | C47: ='DIAGNOSTICO GESTIÓN AMBIENTAL'!N256 -> Promedio
B48: 61 | C48: ='DIAGNOSTICO GESTIÓN AMBIENTAL'!N263 -> Promedio
B49: 62 | C49: ='DIAGNOSTICO GESTIÓN AMBIENTAL'!N270 -> Promedio
B50: 63 | C50: ='DIAGNOSTICO GESTIÓN AMBIENTAL'!N277 -> Promedio
B51: 64 | C51: ='DIAGNOSTICO GESTIÓN AMBIENTAL'!N284 -> Promedio
B52: 65 | C52: ='DIAGNOSTICO GESTIÓN AMBIENTAL'!N291 -> Promedio
B53: 66 | C53: ='DIAGNOSTICO GESTIÓN AMBIENTAL'!N298 -> Promedio
B54: 67 | C54: ='DIAGNOSTICO GESTIÓN AMBIENTAL'!N305 -> Promedio
B55: 68 | C55: ='DIAGNOSTICO GESTIÓN AMBIENTAL'!N312 -> Promedio
B56: 69 | C56: ='DIAGNOSTICO GESTIÓN AMBIENTAL'!N319 -> Promedio
B57: 70 | C57: ='DIAGNOSTICO GESTIÓN AMBIENTAL'!N326 -> Promedio
B58: 71 | C58: ='DIAGNOSTICO GESTIÓN AMBIENTAL'!N333 -> Promedio
B59: 72 | C59: ='DIAGNOSTICO GESTIÓN AMBIENTAL'!N340 -> Promedio
B60: 73 | C60: ='DIAGNOSTICO GESTIÓN AMBIENTAL'!N347 -> Promedio
B61: 74 | C61: ='DIAGNOSTICO GESTIÓN AMBIENTAL'!N354 -> Promedio
B62: 75 | C62: ='DIAGNOSTICO GESTIÓN AMBIENTAL'!N361 -> Promedio
B63: 76 | C63: ='DIAGNOSTICO GESTIÓN AMBIENTAL'!N368 -> Promedio
B64: 77 | C64: ='DIAGNOSTICO GESTIÓN AMBIENTAL'!N375 -> Promedio
B65: 78 | C65: ='DIAGNOSTICO GESTIÓN AMBIENTAL'!N382 -> Promedio
B66: 79 | C66: ='DIAGNOSTICO GESTIÓN AMBIENTAL'!N389 -> Promedio
B67: 80 | C67: ='DIAGNOSTICO GESTIÓN AMBIENTAL'!N396 -> Promedio
B68: 81 | C68: ='DIAGNOSTICO GESTIÓN AMBIENTAL'!N403 -> Promedio
B69: 82 | C69: ='DIAGNOSTICO GESTIÓN AMBIENTAL'!N410 -> Promedio
B70: 83 | C70: ='DIAGNOSTICO GESTIÓN AMBIENTAL'!N417 -> Promedio
B71: 84 | C71: ='DIAGNOSTICO GESTIÓN AMBIENTAL'!N424 -> Promedio
B72: 85 | C72: ='DIAGNOSTICO GESTIÓN AMBIENTAL'!N431 -> Promedio
B73: 86 | C73: ='DIAGNOSTICO GESTIÓN AMBIENTAL'!N438 -> Promedio
B74: 87 | C74: ='DIAGNOSTICO GESTIÓN AMBIENTAL'!N445 -> Promedio
B75: 88 | C75: ='DIAGNOSTICO GESTIÓN AMBIENTAL'!N452 -> Promedio
B76: 89 | C76: ='DIAGNOSTICO GESTIÓN AMBIENTAL'!N459 -> Promedio
B77: 90 | C77: ='DIAGNOSTICO GESTIÓN AMBIENTAL'!N466 -> Promedio
B78: 91 | C78: ='DIAGNOSTICO GESTIÓN AMBIENTAL'!N473 -> Promedio
B80: B6. Gestión de residuos sólidos
B81: 92 | C81: ='DIAGNOSTICO GESTIÓN AMBIENTAL'!N483 -> Promedio
B82: 93 | C82: ='DIAGNOSTICO GESTIÓN AMBIENTAL'!N490 -> Promedio
B83: 94 | C83: ='DIAGNOSTICO GESTIÓN AMBIENTAL'!N497 -> Promedio
B84: 95 | C84: ='DIAGNOSTICO GESTIÓN AMBIENTAL'!N504 -> Promedio
B85: 96 | C85: ='DIAGNOSTICO GESTIÓN AMBIENTAL'!N511 -> Promedio
B86: 97 | C86: ='DIAGNOSTICO GESTIÓN AMBIENTAL'!N518 -> Promedio
B87: 98 | C87: ='DIAGNOSTICO GESTIÓN AMBIENTAL'!N525 -> Promedio
B88: 99 | C88: ='DIAGNOSTICO GESTIÓN AMBIENTAL'!N532 -> Promedio
B89: 100 | C89: ='DIAGNOSTICO GESTIÓN AMBIENTAL'!N539 -> Promedio
B90: 101 | C90: ='DIAGNOSTICO GESTIÓN AMBIENTAL'!N546 -> Promedio
B91: 102 | C91: ='DIAGNOSTICO GESTIÓN AMBIENTAL'!N553 -> Promedio
B92: 103 | C92: ='DIAGNOSTICO GESTIÓN AMBIENTAL'!N560 -> Promedio

Sheet DIAGNOSTICO ENERGIA
B2: Aspectos ambientales
B4: C. Gestión energía
E5: 3 | G5: 2 | I5: 1 | K5: 0
B6: C1. Tipo y clase de energía consumida
B8: 104.- | C8: ¿Existen medidores de energía?
F10: IMP | H10: M | J10: AC | L10: NA | M10: =IF(E10="X","",IF(G10="X","",IF(I10="X","",IF(K10="X","","Elegir opción")))) -> Elegir opción | N10: =IF(E10="X",3,IF(G10="X",2,IF(I10="X",1,IF(K10="X",0,"Promedio")))) -> Promedio
B15: 105.- | C15: ¿Los equipos funcionan con energía eléctrica?
F17: IMP | H17: M | J17: AC | L17: NA | M17: =IF(E17="X","",IF(G17="X","",IF(I17="X","",IF(K17="X","","Elegir opción")))) -> Elegir opción | N17: =IF(E17="X",3,IF(G17="X",2,IF(I17="X",1,IF(K17="X",0,"Promedio")))) -> Promedio
B22: 106.- | C22: ¿Existen fichas técnicas de los equipos?
F24: IMP | H24: M | J24: AC | L24: NA | M24: =IF(E24="X","",IF(G24="X","",IF(I24="X","",IF(K24="X","","Elegir opción")))) -> Elegir opción | N24: =IF(E24="X",3,IF(G24="X",2,IF(I24="X",1,IF(K24="X",0,"Promedio")))) -> Promedio
B29: 107.- | C29: ¿Las condiciones eléctricas son adecuadas?
F31: IMP | H31: M | J31: AC | L31: NA | M31: =IF(E31="X","",IF(G31="X","",IF(I31="X","",IF(K31="X","","Elegir opción")))) -> Elegir opción | N31: =IF(E31="X",3,IF(G31="X",2,IF(I31="X",1,IF(K31="X",0,"Promedio")))) -> Promedio
B36: 108.- | C36: ¿Los elementos de protección son los adecuados para prevenir el riesgo?
F38: IMP | H38: M | J38: AC | L38: NA | M38: =IF(E38="X","",IF(G38="X","",IF(I38="X","",IF(K38="X","","Elegir opción")))) -> Elegir opción | N38: =IF(E38="X",3,IF(G38="X",2,IF(I38="X",1,IF(K38="X",0,"Promedio")))) -> Promedio
B43: 109.- | C43: ¿Se ha realizado capacitación en riesgo eléctrico?
F45: IMP | H45: M | J45: AC | L45: NA | M45: =IF(E45="X","",IF(G45="X","",IF(I45="X","",IF(K45="X","","Elegir opción")))) -> Elegir opción | N45: =IF(E45="X",3,IF(G45="X",2,IF(I45="X",1,IF(K45="X",0,"Promedio")))) -> Promedio
B50: 110.- | C50: ¿Existe un plano de la red eléctrica de la instalación?
F52: IMP | H52: M | J52: AC | L52: NA | M52: =IF(E52="X","",IF(G52="X","",IF(I52="X","",IF(K52="X","","Elegir opción")))) -> Elegir opción | N52: =IF(E52="X",3,IF(G52="X",2,IF(I52="X",1,IF(K52="X",0,"Promedio")))) -> Promedio
B57: 111.- | C57: ¿Se tiene la señalización pertinente para riesgos eléctricos?
F59: IMP | H59: M | J59: AC | L59: NA | M59: =IF(E59="X","",IF(G59="X","",IF(I59="X","",IF(K59="X","","Elegir opción")))) -> Elegir opción | N59: =IF(E59="X",3,IF(G59="X",2,IF(I59="X",1,IF(K59="X",0,"Promedio")))) -> Promedio
B65: C2.- Cantidad de energía consumida
B67: 112.- | C67: ¿Existen registro de consumo de energía por KW?
F69: IMP | H69: M | J69: AC | L69: NA | M69: =IF(E69="X","",IF(G69="X","",IF(I69="X","",IF(K69="X","","Elegir opción")))) -> Elegir opción | N69: =IF(E69="X",3,IF(G69="X",2,IF(I69="X",1,IF(K69="X",0,"Promedio")))) -> Promedio
B74: 113.- | C74: ¿Se ha establecido una frecuencia de registro?
F76: IMP | H76: M | J76: AC | L76: NA | M76: =IF(E76="X","",IF(G76="X","",IF(I76="X","",IF(K76="X","","Elegir opción")))) -> Elegir opción | N76: =IF(E76="X",3,IF(G76="X",2,IF(I76="X",1,IF(K76="X",0,"Promedio")))) -> Promedio
B81: 114.- | C81: ¿Aplican un método para ahorrar energía?
F83: IMP | H83: M | J83: AC | L83: NA | M83: =IF(E83="X","",IF(G83="X","",IF(I83="X","",IF(K83="X","","Elegir opción")))) -> Elegir opción | N83: =IF(E83="X",3,IF(G83="X",2,IF(I83="X",1,IF(K83="X",0,"Promedio")))) -> Promedio
B88: 115.- | C88: ¿Se ha tenido riesgo eléctrico en el área?
F90: IMP | H90: M | J90: AC | L90: NA | M90: =IF(E90="X","",IF(G90="X","",IF(I90="X","",IF(K90="X","","Elegir opción")))) -> Elegir opción | N90: =IF(E90="X",3,IF(G90="X",2,IF(I90="X",1,IF(K90="X",0,"Promedio")))) -> Promedio
B95: 116.- | C95: ¿Existen equipos de protección para riesgos eléctricos?
F97: IMP | H97: M | J97: AC | L97: NA | M97: =IF(E97="X","",IF(G97="X","",IF(I97="X","",IF(K97="X","","Elegir opción")))) -> Elegir opción | N97: =IF(E97="X",3,IF(G97="X",2,IF(I97="X",1,IF(K97="X",0,"Promedio")))) -> Promedio
B103: C3.- Posibilidad de Cambio tecnológico para el consumo de energía
B105: 117.- | C105: ¿Existen equipos de consumo a gas?
F107: IMP | H107: M | J107: AC | L107: NA | M107: =IF(E107="X","",IF(G107="X","",IF(I107="X","",IF(K107="X","","Elegir opción")))) -> Elegir opción | N107: =IF(E107="X",3,IF(G107="X",2,IF(I107="X",1,IF(K107="X",0,"Promedio")))) -> Promedio
B112: 118.- | C112: ¿Existen registros de consumo a gas?
F114: IMP | H114: M | J114: AC | L114: NA | M114: =IF(E114="X","",IF(G114="X","",IF(I114="X","",IF(K114="X","","Elegir opción")))) -> Elegir opción | N114: =IF(E114="X",3,IF(G114="X",2,IF(I114="X",1,IF(K114="X",0,"Promedio")))) -> Promedio
B119: 119.- | C119: Existe posibilidades de cambio en las tecnologías para el consumo de energía por energías limpias (eólica, solar, gas, entre otras).
F121: IMP | H121: M | J121: AC | L121: NA | M121: =IF(E121="X","",IF(G121="X","",IF(I121="X","",IF(K121="X","","Elegir opción")))) -> Elegir opción | N121: =IF(E121="X",3,IF(G121="X",2,IF(I121="X",1,IF(K121="X",0,"Promedio")))) -> Promedio

Sheet DATOS C.
B2: Diagnóstico energía
B4: C1. Tipo y clase de energía consumida
B5: Item | C5: Diagnóstico promedial
B6: 104 | C6: ='DIAGNOSTICO ENERGIA'!N10 -> Promedio
B7: 105 | C7: ='DIAGNOSTICO ENERGIA'!N17 -> Promedio | G7: C1 | H7: =SUMIF(C6:C13,">0",C6:C13)/COUNTIF(C6:C13,">0") -> #DIV/0!
B8: 106 | C8: ='DIAGNOSTICO ENERGIA'!N24 -> Promedio | G8: C2 | H8: =SUMIF(C16:C20,">0",C16:C20)/COUNTIF(C16:C20,">0") -> #DIV/0!
B9: 107 | C9: ='DIAGNOSTICO ENERGIA'!N31 -> Promedio | G9: C3 | H9: =SUMIF(C23:C25,">0",C23:C25)/COUNTIF(C23:C25,">0") -> #DIV/0!
B10: 108 | C10: ='DIAGNOSTICO ENERGIA'!N38 -> Promedio
B11: 109 | C11: ='DIAGNOSTICO ENERGIA'!N45 -> Promedio | G11: Diagnóstico energía | H11: =((SUM(H7:H10)/3)*100)/3 -> #DIV/0!
B12: 110 | C12: ='DIAGNOSTICO ENERGIA'!N52 -> Promedio
B13: 111 | C13: ='DIAGNOSTICO ENERGIA'!N59 -> Promedio
B15: C2.- Cantidad de energía consumida
B16: 112 | C16: ='DIAGNOSTICO ENERGIA'!N69 -> Promedio
B17: 113 | C17: ='DIAGNOSTICO ENERGIA'!N76 -> Promedio
B18: 114 | C18: ='DIAGNOSTICO ENERGIA'!N83 -> Promedio
B19: 115 | C19: ='DIAGNOSTICO ENERGIA'!N90 -> Promedio
B20: 116 | C20: ='DIAGNOSTICO ENERGIA'!N97 -> Promedio
B22: C3.- Posibilidad de Cambio tecnológico para el consumo de energía.
B23: 117 | C23: ='DIAGNOSTICO ENERGIA'!N107 -> Promedio
B24: 118 | C24: ='DIAGNOSTICO ENERGIA'!N114 -> Promedio
B25: 119 | C25: ='DIAGNOSTICO ENERGIA'!N121 -> Promedio

Sheet DIAGNOSTICO SEGURIDAD Y SALUD E
B2: Aspectos ambientales
B4: D. Gestión de Seguridad y Salud en el Trabajo
E6: 3 | G6: 2 | I6: 1 | K6: 0
B7: D1. Normatividad
B8: 120.- | C8: ¿Se aplica la normatividad de Seguridad y Salud en el Trabajo?
F10: IMP | H10: M | J10: AC | L10: NA | M10: =IF(E10="X","",IF(G10="X","",IF(I10="X","",IF(K10="X","","Elegir opción")))) -> Elegir opción | N10: =IF(E10="X",3,IF(G10="X",2,IF(I10="X",1,IF(K10="X",0,"Promedio")))) -> Promedio
B15: D2. Documentación
B16: 121.- | C16: ¿Se encuentra documentado el programa de Seguridad y Salud en el Trabajo?
F18: IMP | H18: M | J18: AC | L18: NA | M18: =IF(E18="X","",IF(G18="X","",IF(I18="X","",IF(K18="X","","Elegir opción")))) -> Elegir opción | N18: =IF(E18="X",3,IF(G18="X",2,IF(I18="X",1,IF(K18="X",0,"Promedio")))) -> Promedio
B23: 122.- | C23: ¿Se tiene elaborado matriz de riesgo?
F25: IMP | H25: M | J25: AC | L25: NA | M25: =IF(E25="X","",IF(G25="X","",IF(I25="X","",IF(K25="X","","Elegir opción")))) -> Elegir opción | N25: =IF(E25="X",3,IF(G25="X",2,IF(I25="X",1,IF(K25="X",0,"Promedio")))) -> Promedio
B30: 123.- | C30: ¿Se encuentra divulgado e implementado?
F32: IMP | H32: M | J32: AC | L32: NA | M32: =IF(E32="X","",IF(G32="X","",IF(I32="X","",IF(K32="X","","Elegir opción")))) -> Elegir opción | N32: =IF(E32="X",3,IF(G32="X",2,IF(I32="X",1,IF(K32="X",0,"Promedio")))) -> Promedio
B39: D3. Comité paritario
B40: 124.- | C40: ¿Se cuenta con un comité paritario?
F42: IMP | H42: M | J42: AC | L42: NA | M42: =IF(E42="X","",IF(G42="X","",IF(I42="X","",IF(K42="X","","Elegir opción")))) -> Elegir opción | N42: =IF(E42="X",3,IF(G42="X",2,IF(I42="X",1,IF(K42="X",0,"Promedio")))) -> Promedio
B47: 125.- | C47: ¿Existen evidencias del trabajo realizado por dicho comité?
F49: IMP | H49: M | J49: AC | L49: NA | M49: =IF(E49="X","",IF(G49="X","",IF(I49="X","",IF(K49="X","","Elegir opción")))) -> Elegir opción | N49: =IF(E49="X",3,IF(G49="X",2,IF(I49="X",1,IF(K49="X",0,"Promedio")))) -> Promedio
B55: D4. Accidentes
B56: 126.- | C56: ¿Se han reportado los accidentes ocurridos?
F58: IMP | H58: M | J58: AC | L58: NA | M58: =IF(E58="X","",IF(G58="X","",IF(I58="X","",IF(K58="X","","Elegir opción")))) -> Elegir opción | N58: =IF(E58="X",3,IF(G58="X",2,IF(I58="X",1,IF(K58="X",0,"Promedio")))) -> Promedio
B63: 127.- | C63: ¿Se ha identificado y trabajado en las causas de los accidentes reportados?
F65: IMP | H65: M | J65: AC | L65: NA | M65: =IF(E65="X","",IF(G65="X","",IF(I65="X","",IF(K65="X","","Elegir opción")))) -> Elegir opción | N65: =IF(E65="X",3,IF(G65="X",2,IF(I65="X",1,IF(K65="X",0,"Promedio")))) -> Promedio
B70: 128.- | C70: ¿Se tiene identificada la frecuencia con la que ocurren?
F72: IMP | H72: M | J72: AC | L72: NA | M72: =IF(E72="X","",IF(G72="X","",IF(I72="X","",IF(K72="X","","Elegir opción")))) -> Elegir opción | N72: =IF(E72="X",3,IF(G72="X",2,IF(I72="X",1,IF(K72="X",0,"Promedio")))) -> Promedio
B77: 129.- | C77: ¿Los accidentes presentados han generado algún impacto ambiental?
F79: IMP | H79: M | J79: AC | L79: NA | M79: =IF(E79="X","",IF(G79="X","",IF(I79="X","",IF(K79="X","","Elegir opción")))) -> Elegir opción | N79: =IF(E79="X",3,IF(G79="X",2,IF(I79="X",1,IF(K79="X",0,"Promedio")))) -> Promedio
B84: 130.- | C84: ¿Se conocen casos de enfermedades profesionales?
F86: IMP | H86: M | J86: AC | L86: NA | M86: =IF(E86="X","",IF(G86="X","",IF(I86="X","",IF(K86="X","","Elegir opción")))) -> Elegir opción | N86: =IF(E86="X",3,IF(G86="X",2,IF(I86="X",1,IF(K86="X",0,"Promedio")))) -> Promedio
B92: D5. Incidentes
B93: 131.- | C93: ¿Se han reportado los incidentes ocurridos?
F95: IMP | H95: M | J95: AC | L95: NA | M95: =IF(E95="X","",IF(G95="X","",IF(I95="X","",IF(K95="X","","Elegir opción")))) -> Elegir opción | N95: =IF(E95="X",3,IF(G95="X",2,IF(I95="X",1,IF(K95="X",0,"Promedio")))) -> Promedio
B100: 132.- | C100: ¿Se han identificado y trabajado en las causas de los incidentes reportados?
F102: IMP | H102: M | J102: AC | L102: NA | M102: =IF(E102="X","",IF(G102="X","",IF(I102="X","",IF(K102="X","","Elegir opción")))) -> Elegir opción | N102: =IF(E102="X",3,IF(G102="X",2,IF(I102="X",1,IF(K102="X",0,"Promedio")))) -> Promedio
B107: 133.- | C107: ¿Se tiene identificada la frecuencia con la que ocurren?
F109: IMP | H109: M | J109: AC | L109: NA | M109: =IF(E109="X","",IF(G109="X","",IF(I109="X","",IF(K109="X","","Elegir opción")))) -> Elegir opción | N109: =IF(E109="X",3,IF(G109="X",2,IF(I109="X",1,IF(K109="X",0,"Promedio")))) -> Promedio
B114: 134.- | C114: ¿Los incidentes identificados han generado algún impacto ambiental?
F116: IMP | H116: M | J116: AC | L116: NA | M116: =IF(E116="X","",IF(G116="X","",IF(I116="X","",IF(K116="X","","Elegir opción")))) -> Elegir opción | N116: =IF(E116="X",3,IF(G116="X",2,IF(I116="X",1,IF(K116="X",0,"Promedio")))) -> Promedio
B122: D6 Planes de emergencia
B123: 135.- | C123: ¿Existen planes de contingencia o emergencia?
F125: IMP | H125: M | J125: AC | L125: NA | M125: =IF(E125="X","",IF(G125="X","",IF(I125="X","",IF(K125="X","","Elegir opción")))) -> Elegir opción | N125: =IF(E125="X",3,IF(G125="X",2,IF(I125="X",1,IF(K125="X",0,"Promedio")))) -> Promedio
B130: 136.- | C130: Si existen, ¿se encuentran documentados, divulgados e implementados?
F132: IMP | H132: M | J132: AC | L132: NA | M132: =IF(E132="X","",IF(G132="X","",IF(I132="X","",IF(K132="X","","Elegir opción")))) -> Elegir opción | N132: =IF(E132="X",3,IF(G132="X",2,IF(I132="X",1,IF(K132="X",0,"Promedio")))) -> Promedio
B137: 137.- | C137: ¿Está conformada una brigada de emergencia capacitada para atender cualquier tipo de eventualidades?
F139: IMP | H139: M | J139: AC | L139: NA | M139: =IF(E139="X","",IF(G139="X","",IF(I139="X","",IF(K139="X","","Elegir opción")))) -> Elegir opción | N139: =IF(E139="X",3,IF(G139="X",2,IF(I139="X",1,IF(K139="X",0,"Promedio")))) -> Promedio
B144: 138.- | C144: ¿Se han realizado simulacros de atención de emergencia?
F146: IMP | H146: M | J146: AC | L146: NA | M146: =IF(E146="X","",IF(G146="X","",IF(I146="X","",IF(K146="X","","Elegir opción")))) -> Elegir opción | N146: =IF(E146="X",3,IF(G146="X",2,IF(I146="X",1,IF(K146="X",0,"Promedio")))) -> Promedio
B151: 139.- | C151: En caso afirmativo, ¿Se tiene identificada la frecuencia con la que se han realizado?
F153: IMP | H153: M | J153: AC | L153: NA | M153: =IF(E153="X","",IF(G153="X","",IF(I153="X","",IF(K153="X","","Elegir opción")))) -> Elegir opción | N153: =IF(E153="X",3,IF(G153="X",2,IF(I153="X",1,IF(K153="X",0,"Promedio")))) -> Promedio
B158: D7. Señalización
B159: 140.- | C159: ¿Existe señalización acorde a las normas legales vigentes (Advertencia, Peligro, Ruta de Evacuación)?
F161: IMP | H161: M | J161: AC | L161: NA | M161: =IF(E161="X","",IF(G161="X","",IF(I161="X","",IF(K161="X","","Elegir opción")))) -> Elegir opción | N161: =IF(E161="X",3,IF(G161="X",2,IF(I161="X",1,IF(K161="X",0,"Promedio")))) -> Promedio
B166: D8. Elementos de Protección Personal
B167: 141.- | C167: ¿Se cuenta con los elementos de protección necesarios según factores de riesgo?
F169: IMP | H169: M | J169: AC | L169: NA | M169: =IF(E169="X","",IF(G169="X","",IF(I169="X","",IF(K169="X","","Elegir opción")))) -> Elegir opción | N169: =IF(E169="X",3,IF(G169="X",2,IF(I169="X",1,IF(K169="X",0,"Promedio")))) -> Promedio
B174: 142.- | C174: ¿Existe evidencia del suministro de los elementos de protección necesarios con la frecuencia indicada?
F176: IMP | H176: M | J176: AC | L176: NA | M176: =IF(E176="X","",IF(G176="X","",IF(I176="X","",IF(K176="X","","Elegir opción")))) -> Elegir opción | N176: =IF(E176="X",3,IF(G176="X",2,IF(I176="X",1,IF(K176="X",0,"Promedio")))) -> Promedio
B181: 143.- | C181: ¿Se vigila que el personal utilice los elementos de protección suministrados de manera adecuada durante el desarrollo de la labor?
F183: IMP | H183: M | J183: AC | L183: NA | M183: =IF(E183="X","",IF(G183="X","",IF(I183="X","",IF(K183="X","","Elegir opción")))) -> Elegir opción | N183: =IF(E183="X",3,IF(G183="X",2,IF(I183="X",1,IF(K183="X",0,"Promedio")))) -> Promedio
B188: 144.- | C188: ¿Se ha capacitado al personal sobre la importancia del uso adecuado de los elementos de protección suministrados y la manera adecuada de utilizarlos?
F190: IMP | H190: M | J190: AC | L190: NA | M190: =IF(E190="X","",IF(G190="X","",IF(I190="X","",IF(K190="X","","Elegir opción")))) -> Elegir opción | N190: =IF(E190="X",3,IF(G190="X",2,IF(I190="X",1,IF(K190="X",0,"Promedio")))) -> Promedio
B196: D9. Uso de extintores
B197: 145.- | C197: ¿Están identificados y clasificados los riesgos (físicos, químicos y biológicos) de acuerdo a los diferentes puestos de trabajo?
F199: IMP | H199: M | J199: AC | L199: NA | M199: =IF(E199="X","",IF(G199="X","",IF(I199="X","",IF(K199="X","","Elegir opción")))) -> Elegir opción | N199: =IF(E199="X",3,IF(G199="X",2,IF(I199="X",1,IF(K199="X",0,"Promedio")))) -> Promedio
B204: 146.- | C204: ¿La distribución y ubicación de los extintores obedece a la reglamentación legal?
F206: IMP | H206: M | J206: AC | L206: NA | M206: =IF(E206="X","",IF(G206="X","",IF(I206="X","",IF(K206="X","","Elegir opción")))) -> Elegir opción | N206: =IF(E206="X",3,IF(G206="X",2,IF(I206="X",1,IF(K206="X",0,"Promedio")))) -> Promedio
B211: 147.- | C211: ¿Existen evidencias de los registros de mantenimiento de los extintores?
F213: IMP | H213: M | J213: AC | L213: NA | M213: =IF(E213="X","",IF(G213="X","",IF(I213="X","",IF(K213="X","","Elegir opción")))) -> Elegir opción | N213: =IF(E213="X",3,IF(G213="X",2,IF(I213="X",1,IF(K213="X",0,"Promedio")))) -> Promedio
B218: 148.- | C218: ¿Se controla la vigencia de los extintores?
F220: IMP | H220: M | J220: AC | L220: NA | M220: =IF(E220="X","",IF(G220="X","",IF(I220="X","",IF(K220="X","","Elegir opción")))) -> Elegir opción | N220: =IF(E220="X",3,IF(G220="X",2,IF(I220="X",1,IF(K220="X",0,"Promedio")))) -> Promedio
B225: 149.- | C225: ¿Se ha capacitado al personal sobre el uso adecuado de los extintores?
F227: IMP | H227: M | J227: AC | L227: NA | M227: =IF(E227="X","",IF(G227="X","",IF(I227="X","",IF(K227="X","","Elegir opción")))) -> Elegir opción | N227: =IF(E227="X",3,IF(G227="X",2,IF(I227="X",1,IF(K227="X",0,"Promedio")))) -> Promedio
B233: D10.Panorama de factores de riesgo
B234: 150.- | C234: ¿Están identificados y clasificados los riesgos (físicos, químicos y biológicos) de acuerdo a los diferentes puestos de trabajo?
F236: IMP | H236: M | J236: AC | L236: NA | M236: =IF(E236="X","",IF(G236="X","",IF(I236="X","",IF(K236="X","","Elegir opción")))) -> Elegir opción | N236: =IF(E236="X",3,IF(G236="X",2,IF(I236="X",1,IF(K236="X",0,"Promedio")))) -> Promedio
B241: 151.- | C241: ¿Existen métodos de control para identificar nuevos factores de riesgos?
F243: IMP | H243: M | J243: AC | L243: NA | M243: =IF(E243="X","",IF(G243="X","",IF(I243="X","",IF(K243="X","","Elegir opción")))) -> Elegir opción | N243: =IF(E243="X",3,IF(G243="X",2,IF(I243="X",1,IF(K243="X",0,"Promedio")))) -> Promedio
B248: 152.- | C248: ¿Existen planos actualizados de las diferentes áreas para identificar y ubicar factores de riesgo?
F250: IMP | H250: M | J250: AC | L250: NA | M250: =IF(E250="X","",IF(G250="X","",IF(I250="X","",IF(K250="X","","Elegir opción")))) -> Elegir opción | N250: =IF(E250="X",3,IF(G250="X",2,IF(I250="X",1,IF(K250="X",0,"Promedio")))) -> Promedio
B255: 153.- | C255: ¿Se tienen acciones frente a los diferentes riesgos existentes?
F257: IMP | H257: M | J257: AC | L257: NA | M257: =IF(E257="X","",IF(G257="X","",IF(I257="X","",IF(K257="X","","Elegir opción")))) -> Elegir opción | N257: =IF(E257="X",3,IF(G257="X",2,IF(I257="X",1,IF(K257="X",0,"Promedio")))) -> Promedio

Sheet DATOS D.
B2: Diagnóstico Seguridad y Salud en el Trabajo
B4: D1. Normatividad
B5: Item | C5: Diagnóstico promedial
B6: 120 | C6: ='DIAGNOSTICO SEGURIDAD Y SALUD E'!N10 -> Promedio
B8: D2. Documentación | F8: D1 | G8: =SUMIF(C6:C6,">0",C6:C6)/COUNTIF(C6:C6,">0") -> #DIV/0!
B9: 121 | C9: ='DIAGNOSTICO SEGURIDAD Y SALUD E'!N18 -> Promedio | F9: D2 | G9: =SUMIF(C9:C11,">0",C9:C11)/COUNTIF(C9:C11,">0") -> #DIV/0!
B10: 122 | C10: ='DIAGNOSTICO SEGURIDAD Y SALUD E'!N25 -> Promedio | F10: D3 | G10: =SUMIF(C14:C15,">0",C14:C15)/COUNTIF(C14:C15,">0") -> #DIV/0!
B11: 123 | C11: ='DIAGNOSTICO SEGURIDAD Y SALUD E'!N32 -> Promedio | F11: D4 | G11: =SUMIF(C18:C22,">0",C18:C22)/COUNTIF(C18:C22,">0") -> #DIV/0!
F12: D5 | G12: =SUMIF(C25:C28,">0",C25:C28)/COUNTIF(C25:C28,">0") -> #DIV/0!
B13: D3. Comité Paritario | F13: D6 | G13: =SUMIF(C31:C35,">0",C31:C35)/COUNTIF(C31:C35,">0") -> #DIV/0!
B14: 124 | C14: ='DIAGNOSTICO SEGURIDAD Y SALUD E'!N42 -> Promedio | F14: D7 | G14: =SUMIF(C38:C38,">0",C38:C38)/COUNTIF(C38:C38,">0") -> #DIV/0!
B15: 125 | C15: ='DIAGNOSTICO SEGURIDAD Y SALUD E'!N49 -> Promedio | F15: D8 | G15: =SUMIF(C41:C44,">0",C41:C44)/COUNTIF(C41:C44,">0") -> #DIV/0!
F16: D9 | G16: =SUMIF(C47:C51,">0",C47:C51)/COUNTIF(C47:C51,">0") -> #DIV/0!
B17: D4. Accidentes | F17: D10 | G17: =SUMIF(C54:C57,">0",C54:C57)/COUNTIF(C54:C57,">0") -> #DIV/0!
B18: 126 | C18: ='DIAGNOSTICO SEGURIDAD Y SALUD E'!N58 -> Promedio
B19: 127 | C19: ='DIAGNOSTICO SEGURIDAD Y SALUD E'!N65 -> Promedio | F19: Diagnóstico salud ocupacional | G19: =((SUM(G8:G17)/10)*100)/10 -> #DIV/0!
B20: 128 | C20: ='DIAGNOSTICO SEGURIDAD Y SALUD E'!N72 -> Promedio
B21: 129 | C21: ='DIAGNOSTICO SEGURIDAD Y SALUD E'!N79 -> Promedio
B22: 130 | C22: ='DIAGNOSTICO SEGURIDAD Y SALUD E'!N86 -> Promedio
B24: D5. Incidentes
B25: 131 | C25: ='DIAGNOSTICO SEGURIDAD Y SALUD E'!N95 -> Promedio
B26: 132 | C26: ='DIAGNOSTICO SEGURIDAD Y SALUD E'!N102 -> Promedio
B27: 133 | C27: ='DIAGNOSTICO SEGURIDAD Y SALUD E'!N109 -> Promedio
B28: 134 | C28: ='DIAGNOSTICO SEGURIDAD Y SALUD E'!N116 -> Promedio
B30: D6 Planes de emergencia
B31: 135 | C31: ='DIAGNOSTICO SEGURIDAD Y SALUD E'!N125 -> Promedio
B32: 136 | C32: ='DIAGNOSTICO SEGURIDAD Y SALUD E'!N132 -> Promedio
B33: 137 | C33: ='DIAGNOSTICO SEGURIDAD Y SALUD E'!N139 -> Promedio
B34: 138 | C34: ='DIAGNOSTICO SEGURIDAD Y SALUD E'!N146 -> Promedio
B35: 139 | C35: ='DIAGNOSTICO SEGURIDAD Y SALUD E'!N153 -> Promedio
B37: D7. Señalización
B38: 140 | C38: ='DIAGNOSTICO SEGURIDAD Y SALUD E'!N161 -> Promedio
B40: D8. Elementos de protección personal
B41: 141 | C41: ='DIAGNOSTICO SEGURIDAD Y SALUD E'!N169 -> Promedio
B42: 142 | C42: ='DIAGNOSTICO SEGURIDAD Y SALUD E'!N176 -> Promedio
B43: 143 | C43: ='DIAGNOSTICO SEGURIDAD Y SALUD E'!N183 -> Promedio
B44: 144 | C44: ='DIAGNOSTICO SEGURIDAD Y SALUD E'!N190 -> Promedio
B46: D9. Uso de extintores
B47: 145 | C47: ='DIAGNOSTICO SEGURIDAD Y SALUD E'!N199 -> Promedio
B48: 146 | C48: ='DIAGNOSTICO SEGURIDAD Y SALUD E'!N206 -> Promedio
B49: 147 | C49: ='DIAGNOSTICO SEGURIDAD Y SALUD E'!N213 -> Promedio
B50: 148 | C50: ='DIAGNOSTICO SEGURIDAD Y SALUD E'!N220 -> Promedio
B51: 149 | C51: ='DIAGNOSTICO SEGURIDAD Y SALUD E'!N227 -> Promedio
B53: D10.Panorama de factores de riesgo
B54: 150 | C54: ='DIAGNOSTICO SEGURIDAD Y SALUD E'!N236 -> Promedio
B55: 151 | C55: ='DIAGNOSTICO SEGURIDAD Y SALUD E'!N243 -> Promedio
B56: 152 | C56: ='DIAGNOSTICO SEGURIDAD Y SALUD E'!N250 -> Promedio
B57: 153 | C57: ='DIAGNOSTICO SEGURIDAD Y SALUD E'!N257 -> Promedio

Sheet DIAGNOSTICO ASPECTOS SOCIALES
B2: Aspectos ambientales
B4: E. Aspectos sociales y responsabilidad social empresarial
E6: 3 | G6: 2 | I6: 1 | K6: 0
B7: E1. Empleo y mecanismos de evaluación
B9: 154.- | C9: La estrategia empresarial se ha formulado de manera que se garantice el empleo a largo plazo.
F11: IMP | H11: M | J11: AC | L11: NA | M11: =IF(E11="X","",IF(G11="X","",IF(I11="X","",IF(K11="X","","Elegir opción")))) -> Elegir opción | N11: =IF(E11="X",3,IF(G11="X",2,IF(I11="X",1,IF(K11="X",0,"Promedio")))) -> Promedio
B16: 155.- | C16: En comparación con otras empresas del sector, la rotación del personal es baja.
F18: IMP | H18: M | J18: AC | L18: NA | M18: =IF(E18="X","",IF(G18="X","",IF(I18="X","",IF(K18="X","","Elegir opción")))) -> Elegir opción | N18: =IF(E18="X",3,IF(G18="X",2,IF(I18="X",1,IF(K18="X",0,"Promedio")))) -> Promedio
B23: 156.- | C23: Dentro de la empresa, todos las personas tienen igualdad de oportunidades, independientemente de edad, religión, género, grupo étnico, discapacidad, orientación sexual, posición económica, o afiliación política y/o grupos de negociación colectiva (por ejemplo, oportunidades de capacitación, representación en puestos gerenciales, tiempos flexibles de trabajo, remuneración, contrataciones, despidos, jubilaciones, etc.)
F25: IMP | H25: M | J25: AC | L25: NA | M25: =IF(E25="X","",IF(G25="X","",IF(I25="X","",IF(K25="X","","Elegir opción")))) -> Elegir opción | N25: =IF(E25="X",3,IF(G25="X",2,IF(I25="X",1,IF(K25="X",0,"Promedio")))) -> Promedio
B30: 157.- | C30: La empresa se esfuerza por crear y mantener oportunidades de práctica para estudiantes.
F32: IMP | H32: M | J32: AC | L32: NA | M32: =IF(E32="X","",IF(G32="X","",IF(I32="X","",IF(K32="X","","Elegir opción")))) -> Elegir opción | N32: =IF(E32="X",3,IF(G32="X",2,IF(I32="X",1,IF(K32="X",0,"Promedio")))) -> Promedio
B38: E2. Protección de la salud y condiciones laborales
B40: 158.- | C40: En la empresa se considera de gran importancia la protección de la salud (tanto de los empleados como del cliente) y se procura la mejora de las condiciones laborales más allá del cumplimiento legal obligatorio.
F42: IMP | H42: M | J42: AC | L42: NA | M42: =IF(E42="X","",IF(G42="X","",IF(I42="X","",IF(K42="X","","Elegir opción")))) -> Elegir opción | N42: =IF(E42="X",3,IF(G42="X",2,IF(I42="X",1,IF(K42="X",0,"Promedio")))) -> Promedio
B47: 159.- | C47: Hasta donde sea posible, se evita el uso de sustancias dañinas para la salud (por ejemplo, sustancias tóxicas). En caso de que no se pueda evitar, se utilizan cantidades mínimas de estas sustancias y se toman las precauciones correspondientes.
F49: IMP | H49: M | J49: AC | L49: NA | M49: =IF(E49="X","",IF(G49="X","",IF(I49="X","",IF(K49="X","","Elegir opción")))) -> Elegir opción | N49: =IF(E49="X",3,IF(G49="X",2,IF(I49="X",1,IF(K49="X",0,"Promedio")))) -> Promedio
B54: 160.- | C54: Dentro de la empresa se ofrecen cursos y se desarrollan programas dirigidos a mejorar la salud (por ejemplo, ejercicios para la espalda, programas de prevención del síndrome RSI (movimientos repetitivos)).
F56: IMP | H56: M | J56: AC | L56: NA | M56: =IF(E56="X","",IF(G56="X","",IF(I56="X","",IF(K56="X","","Elegir opción")))) -> Elegir opción | N56: =IF(E56="X",3,IF(G56="X",2,IF(I56="X",1,IF(K56="X",0,"Promedio")))) -> Promedio
B61: 161.- | C61: En los últimos años, se ha mantenido un nivel bajo de accidentes laborales o se ha logrado una disminución de los mismos.
F63: IMP | H63: M | J63: AC | L63: NA | M63: =IF(E63="X","",IF(G63="X","",IF(I63="X","",IF(K63="X","","Elegir opción")))) -> Elegir opción | N63: =IF(E63="X",3,IF(G63="X",2,IF(I63="X",1,IF(K63="X",0,"Promedio")))) -> Promedio
B68: 162.- | C68: En comparación con otras empresas del sector, la ausencia por razones médicas es baja.
F70: IMP | H70: M | J70: AC | L70: NA | M70: =IF(E70="X","",IF(G70="X","",IF(I70="X","",IF(K70="X","","Elegir opción")))) -> Elegir opción | N70: =IF(E70="X",3,IF(G70="X",2,IF(I70="X",1,IF(K70="X",0,"Promedio")))) -> Promedio
B75: 163.- | C75: En comparación con otras empresas del sector, la ausencia por razones médicas es baja.
F77: IMP | H77: M | J77: AC | L77: NA | M77: =IF(E77="X","",IF(G77="X","",IF(I77="X","",IF(K77="X","","Elegir opción")))) -> Elegir opción | N77: =IF(E77="X",3,IF(G77="X",2,IF(I77="X",1,IF(K77="X",0,"Promedio")))) -> Promedio
B82: 164.- | C82: En la empresa, regularmente se hacen chequeos de las condiciones laborales y de salud.
F84: IMP | H84: M | J84: AC | L84: NA | M84: =IF(E84="X","",IF(G84="X","",IF(I84="X","",IF(K84="X","","Elegir opción")))) -> Elegir opción | N84: =IF(E84="X",3,IF(G84="X",2,IF(I84="X",1,IF(K84="X",0,"Promedio")))) -> Promedio
B90: E3. Capacitación, diversidad e incentivos
B92: 165.- | C92: La alta gerencia promueve la capacitación de los empleados.
F94: IMP | H94: M | J94: AC | L94: NA | M94: =IF(E94="X","",IF(G94="X","",IF(I94="X","",IF(K94="X","","Elegir opción")))) -> Elegir opción | N94: =IF(E94="X",3,IF(G94="X",2,IF(I94="X",1,IF(K94="X",0,"Promedio")))) -> Promedio
B99: 166.- | C99: La oferta de cursos y capacitación dentro de la empresa es buena.
F101: IMP | H101: M | J101: AC | L101: NA | M101: =IF(E101="X","",IF(G101="X","",IF(I101="X","",IF(K101="X","","Elegir opción")))) -> Elegir opción | N101: =IF(E101="X",3,IF(G101="X",2,IF(I101="X",1,IF(K101="X",0,"Promedio")))) -> Promedio
B106: 167.- | C106: Se involucra en forma activa a los empleados en el desarrollo de nuevos objetivos y proyectos, además de que los empleados pueden aportar sus propias iniciativas también.
F108: IMP | H108: M | J108: AC | L108: NA | M108: =IF(E108="X","",IF(G108="X","",IF(I108="X","",IF(K108="X","","Elegir opción")))) -> Elegir opción | N108: =IF(E108="X",3,IF(G108="X",2,IF(I108="X",1,IF(K108="X",0,"Promedio")))) -> Promedio
B113: 168.- | C113: Hasta donde sea posible, la empresa aplica la rotación de puestos.
F115: IMP | H115: M | J115: AC | L115: NA | M115: =IF(E115="X","",IF(G115="X","",IF(I115="X","",IF(K115="X","","Elegir opción")))) -> Elegir opción | N115: =IF(E115="X",3,IF(G115="X",2,IF(I115="X",1,IF(K115="X",0,"Promedio")))) -> Promedio
B120: 169.- | C120: En la empresa se han organizado reuniones periódicas con el personal sobre el desempeño del personal según criterios lógicos y justos para todos los involucrados y donde se define el plan de desarrollo de cada uno.
F122: IMP | H122: M | J122: AC | L122: NA | M122: =IF(E122="X","",IF(G122="X","",IF(I122="X","",IF(K122="X","","Elegir opción")))) -> Elegir opción | N122: =IF(E122="X",3,IF(G122="X",2,IF(I122="X",1,IF(K122="X",0,"Promedio")))) -> Promedio
B127: 170.- | C127: En nuestra empresa se premian los buenos resultados obtenidos y existe un plan de incentivos.
F129: IMP | H129: M | J129: AC | L129: NA | M129: =IF(E129="X","",IF(G129="X","",IF(I129="X","",IF(K129="X","","Elegir opción")))) -> Elegir opción | N129: =IF(E129="X",3,IF(G129="X",2,IF(I129="X",1,IF(K129="X",0,"Promedio")))) -> Promedio
B136: E4. Transparencia e interacción
B138: 171.- | C138: La empresa busca de forma proactiva la comunicación con la comunidad vecina y establece mecanismos para responder de forma directa, abierta y justa a sus solicitudes y quejas.
F140: IMP | H140: M | J140: AC | L140: NA | M140: =IF(E140="X","",IF(G140="X","",IF(I140="X","",IF(K140="X","","Elegir opción")))) -> Elegir opción | N140: =IF(E140="X",3,IF(G140="X",2,IF(I140="X",1,IF(K140="X",0,"Promedio")))) -> Promedio
B145: 172.- | C145: La empresa verifica si todas las empresas en la cadena de producción (desde los proveedores de materia prima hasta los entes encargados de la recolección y procesamiento de los desechos) trabajan según los reglamentos sociales y de salud (por ejemplo, el trabajo infantil).
F147: IMP | H147: M | J147: AC | L147: NA | M147: =IF(E147="X","",IF(G147="X","",IF(I147="X","",IF(K147="X","","Elegir opción")))) -> Elegir opción | N147: =IF(E147="X",3,IF(G147="X",2,IF(I147="X",1,IF(K147="X",0,"Promedio")))) -> Promedio
B152: 173.- | C152: La empresa tiene una política de comunicación y transparencia hacia sus grupos de interés (por ejemplo, a través de informes ambientales, informes sociales, informes financieros, etc.).
F154: IMP | H154: M | J154: AC | L154: NA | M154: =IF(E154="X","",IF(G154="X","",IF(I154="X","",IF(K154="X","","Elegir opción")))) -> Elegir opción | N154: =IF(E154="X",3,IF(G154="X",2,IF(I154="X",1,IF(K154="X",0,"Promedio")))) -> Promedio
B159: 174.- | C159: Existe un diálogo abierto entre nuestra empresa y los diferentes grupos en la sociedad (por ejemplo, el mundo científico, los sindicatos, organizaciones medio ambientales, etc.).
F161: IMP | H161: M | J161: AC | L161: NA | M161: =IF(E161="X","",IF(G161="X","",IF(I161="X","",IF(K161="X","","Elegir opción")))) -> Elegir opción | N161: =IF(E161="X",3,IF(G161="X",2,IF(I161="X",1,IF(K161="X",0,"Promedio")))) -> Promedio
B166: 175.- | C166: La empresa se mantiene dentro de la legalidad y principios éticos en las relaciones comerciales y con otros grupos de interés (por ejemplo, evitando la corrupción).
F168: IMP | H168: M | J168: AC | L168: NA | M168: =IF(E168="X","",IF(G168="X","",IF(I168="X","",IF(K168="X","","Elegir opción")))) -> Elegir opción | N168: =IF(E168="X",3,IF(G168="X",2,IF(I168="X",1,IF(K168="X",0,"Promedio")))) -> Promedio
B173: 176.- | C173: Trabajamos en forma abierta con proveedores, clientes y consumidores para promover un desarrollo sostenible de la empresa.
F175: IMP | H175: M | J175: AC | L175: NA | M175: =IF(E175="X","",IF(G175="X","",IF(I175="X","",IF(K175="X","","Elegir opción")))) -> Elegir opción | N175: =IF(E175="X",3,IF(G175="X",2,IF(I175="X",1,IF(K175="X",0,"Promedio")))) -> Promedio
B180: E5. Social Interno (Se hace mediante encuesta a la cadena de producción de la empresa)
B182: 177.- | C182: ¿Realiza Ud. una adecuada separación de los residuos sólidos que genera?
F184: IMP | H184: M | J184: AC | L184: NA | M184: =IF(E184="X","",IF(G184="X","",IF(I184="X","",IF(K184="X","","Elegir opción")))) -> Elegir opción | N184: =IF(E184="X",3,IF(G184="X",2,IF(I184="X",1,IF(K184="X",0,"Promedio")))) -> Promedio
B189: 178.- | C189: ¿Ha participado en sensibilizaciones internas para el manejo integral de residuos sólidos?
F191: IMP | H191: M | J191: AC | L191: NA | M191: =IF(E191="X","",IF(G191="X","",IF(I191="X","",IF(K191="X","","Elegir opción")))) -> Elegir opción | N191: =IF(E191="X",3,IF(G191="X",2,IF(I191="X",1,IF(K191="X",0,"Promedio")))) -> Promedio
B196: 179.- | C196: ¿Reutiliza el papel que genera en otras actividades?
F198: IMP | H198: M | J198: AC | L198: NA | M198: =IF(E198="X","",IF(G198="X","",IF(I198="X","",IF(K198="X","","Elegir opción")))) -> Elegir opción | N198: =IF(E198="X",3,IF(G198="X",2,IF(I198="X",1,IF(K198="X",0,"Promedio")))) -> Promedio
B203: 180.- | C203: ¿Realiza un consumo adecuado y mínimo del agua cuando la utiliza?
F205: IMP | H205: M | J205: AC | L205: NA | M205: =IF(E205="X","",IF(G205="X","",IF(I205="X","",IF(K205="X","","Elegir opción")))) -> Elegir opción | N205: =IF(E205="X",3,IF(G205="X",2,IF(I205="X",1,IF(K205="X",0,"Promedio")))) -> Promedio
B210: 181.- | C210: ¿Tiene conocimiento de la disposición final de las aguas residuales que se generan dentro de su área de trabajo?
F212: IMP | H212: M | J212: AC | L212: NA | M212: =IF(E212="X","",IF(G212="X","",IF(I212="X","",IF(K212="X","","Elegir opción")))) -> Elegir opción | N212: =IF(E212="X",3,IF(G212="X",2,IF(I212="X",1,IF(K212="X",0,"Promedio")))) -> Promedio
B217: 182.- | C217: ¿Está usted de acuerdo con la instalación de micro medidores de energía y agua para las principales áreas internas?
F219: IMP | H219: M | J219: AC | L219: NA | M219: =IF(E219="X","",IF(G219="X","",IF(I219="X","",IF(K219="X","","Elegir opción")))) -> Elegir opción | N219: =IF(E219="X",3,IF(G219="X",2,IF(I219="X",1,IF(K219="X",0,"Promedio")))) -> Promedio
B224: 183.- | C224: ¿Ha interferido el ruido generado en otras áreas de trabajo, el desempeño de sus actividades?
F226: IMP | H226: M | J226: AC | L226: NA | M226: =IF(E226="X","",IF(G226="X","",IF(I226="X","",IF(K226="X","","Elegir opción")))) -> Elegir opción | N226: =IF(E226="X",3,IF(G226="X",2,IF(I226="X",1,IF(K226="X",0,"Promedio")))) -> Promedio
B231: 184.- | C231: ¿Ha percibido olores desagradables durante el desempeño de sus actividades?
F233: IMP | H233: M | J233: AC | L233: NA | M233: =IF(E233="X","",IF(G233="X","",IF(I233="X","",IF(K233="X","","Elegir opción")))) -> Elegir opción | N233: =IF(E233="X",3,IF(G233="X",2,IF(I233="X",1,IF(K233="X",0,"Promedio")))) -> Promedio
B238: 185.- | C238: ¿Ha presentado problemas de salud debido a estos olores?
F240: IMP | H240: M | J240: AC | L240: NA | M240: =IF(E240="X","",IF(G240="X","",IF(I240="X","",IF(K240="X","","Elegir opción")))) -> Elegir opción | N240: =IF(E240="X",3,IF(G240="X",2,IF(I240="X",1,IF(K240="X",0,"Promedio")))) -> Promedio
B245: 186.- | C245: ¿Cree usted que en su trabajo se han generado otros tipos de problemas de salud?
F247: IMP | H247: M | J247: AC | L247: NA | M247: =IF(E247="X","",IF(G247="X","",IF(I247="X","",IF(K247="X","","Elegir opción")))) -> Elegir opción | N247: =IF(E247="X",3,IF(G247="X",2,IF(I247="X",1,IF(K247="X",0,"Promedio")))) -> Promedio
B252: 187.- | C252: ¿Cree usted que en su área de trabajo se necesita realizar adecuaciones para mejorar su el ambiente de trabajo?
F254: IMP | H254: M | J254: AC | L254: NA | M254: =IF(E254="X","",IF(G254="X","",IF(I254="X","",IF(K254="X","","Elegir opción")))) -> Elegir opción | N254: =IF(E254="X",3,IF(G254="X",2,IF(I254="X",1,IF(K254="X",0,"Promedio")))) -> Promedio
B259: 188.- | C259: ¿Ha percibido olores desagradables durante el desempeño de sus actividades?
F261: IMP | H261: M | J261: AC | L261: NA | M261: =IF(E261="X","",IF(G261="X","",IF(I261="X","",IF(K261="X","","Elegir opción")))) -> Elegir opción | N261: =IF(E261="X",3,IF(G261="X",2,IF(I261="X",1,IF(K261="X",0,"Promedio")))) -> Promedio
B267: E6. Social externo (Se hace mediante encuesta de producción y servicio de los clientes)
B269: 189.- | C269: ¿Se han presentado olores desagradables provenientes de las instalaciones de La empresa?
F271: IMP | H271: M | J271: AC | L271: NA | M271: =IF(E271="X","",IF(G271="X","",IF(I271="X","",IF(K271="X","","Elegir opción")))) -> Elegir opción | N271: =IF(E271="X",3,IF(G271="X",2,IF(I271="X",1,IF(K271="X",0,"Promedio")))) -> Promedio
B276: 190.- | C276: ¿Se han presentado problemas de salud en las personas por causa de estos olores?
F278: IMP | H278: M | J278: AC | L278: NA | M278: =IF(E278="X","",IF(G278="X","",IF(I278="X","",IF(K278="X","","Elegir opción")))) -> Elegir opción | N278: =IF(E278="X",3,IF(G278="X",2,IF(I278="X",1,IF(K278="X",0,"Promedio")))) -> Promedio
B283: 191.- | C283: ¿Se han presentado molestias por causa del ruido generado dentro de la empresa?
F285: IMP | H285: M | J285: AC | L285: NA | M285: =IF(E285="X","",IF(G285="X","",IF(I285="X","",IF(K285="X","","Elegir opción")))) -> Elegir opción | N285: =IF(E285="X",3,IF(G285="X",2,IF(I285="X",1,IF(K285="X",0,"Promedio")))) -> Promedio
B290: 192.- | C290: ¿Le ha generado algún beneficio la cercanía que tiene la empresa con su vivienda?
F292: IMP | H292: M | J292: AC | L292: NA | M292: =IF(E292="X","",IF(G292="X","",IF(I292="X","",IF(K292="X","","Elegir opción")))) -> Elegir opción | N292: =IF(E292="X",3,IF(G292="X",2,IF(I292="X",1,IF(K292="X",0,"Promedio")))) -> Promedio
B297: 193.- | C297: ¿Le ha generado algún perjuicio la cercanía que tiene e la empresa con su vivienda?
F299: IMP | H299: M | J299: AC | L299: NA | M299: =IF(E299="X","",IF(G299="X","",IF(I299="X","",IF(K299="X","","Elegir opción")))) -> Elegir opción | N299: =IF(E299="X",3,IF(G299="X",2,IF(I299="X",1,IF(K299="X",0,"Promedio")))) -> Promedio
B304: 194.- | C304: ¿La empresa le ha generado otros tipos de problemas de salud (aparte de ruido y olores)?
F306: IMP | H306: M | J306: AC | L306: NA | M306: =IF(E306="X","",IF(G306="X","",IF(I306="X","",IF(K306="X","","Elegir opción")))) -> Elegir opción | N306: =IF(E306="X",3,IF(G306="X",2,IF(I306="X",1,IF(K306="X",0,"Promedio")))) -> Promedio

Sheet DATOS E.
B2: Diagnóstico aspectos sociales
B4: E1. Empleo y mecanismos de evaluación
B5: Item | C5: Diagnóstico promedial
B6: 154 | C6: ='DIAGNOSTICO ASPECTOS SOCIALES'!N11 -> Promedio
B7: 155 | C7: ='DIAGNOSTICO ASPECTOS SOCIALES'!N18 -> Promedio
B8: 156 | C8: ='DIAGNOSTICO ASPECTOS SOCIALES'!N25 -> Promedio
B9: 157 | C9: ='DIAGNOSTICO ASPECTOS SOCIALES'!N32 -> Promedio | I9: E1 | J9: =SUMIF(C6:C9,">0",C6:C9)/COUNTIF(C6:C9,">0") -> #DIV/0!
I10: E2 | J10: =SUMIF(C12:C18,">0",C12:C18)/COUNTIF(C12:C18,">0") -> #DIV/0!
B11: E2. Protección de la salud y condiciones laborales | I11: E3 | J11: =SUMIF(C21:C26,">0",C21:C26)/COUNTIF(C21:C26,">0") -> #DIV/0!
B12: 158 | C12: ='DIAGNOSTICO ASPECTOS SOCIALES'!N42 -> Promedio | I12: E4 | J12: =SUMIF(C29:C34,">0",C29:C34)/COUNTIF(C29:C34,">0") -> #DIV/0!
B13: 159 | C13: ='DIAGNOSTICO ASPECTOS SOCIALES'!N49 -> Promedio | I13: E5 | J13: =SUMIF(C37:C48,">0",C37:C48)/COUNTIF(C37:C48,">0") -> #DIV/0!
B14: 160 | C14: ='DIAGNOSTICO ASPECTOS SOCIALES'!N56 -> Promedio | I14: E6 | J14: =SUMIF(C51:C56,">0",C51:C56)/COUNTIF(C51:C56,">0") -> #DIV/0!
B15: 161 | C15: ='DIAGNOSTICO ASPECTOS SOCIALES'!N63 -> Promedio
B16: 162 | C16: ='DIAGNOSTICO ASPECTOS SOCIALES'!N70 -> Promedio | I16: Diagnóstico aspectos sociales | J16: =((SUM(J9:J15)/6)*100)/6 -> #DIV/0!
B17: 163 | C17: ='DIAGNOSTICO ASPECTOS SOCIALES'!N77 -> Promedio
B18: 164 | C18: ='DIAGNOSTICO ASPECTOS SOCIALES'!N84 -> Promedio
B20: E3. Capacitación, diversidad e incentivos
B21: 165 | C21: ='DIAGNOSTICO ASPECTOS SOCIALES'!N94 -> Promedio
B22: 166 | C22: ='DIAGNOSTICO ASPECTOS SOCIALES'!N101 -> Promedio
B23: 167 | C23: ='DIAGNOSTICO ASPECTOS SOCIALES'!N108 -> Promedio
B24: 168 | C24: ='DIAGNOSTICO ASPECTOS SOCIALES'!N115 -> Promedio
B25: 169 | C25: ='DIAGNOSTICO ASPECTOS SOCIALES'!N122 -> Promedio
B26: 170 | C26: ='DIAGNOSTICO ASPECTOS SOCIALES'!N129 -> Promedio
B28: E4. Transparencia e interacción
B29: 171 | C29: ='DIAGNOSTICO ASPECTOS SOCIALES'!N140 -> Promedio
B30: 172 | C30: ='DIAGNOSTICO ASPECTOS SOCIALES'!N147 -> Promedio
B31: 173 | C31: ='DIAGNOSTICO ASPECTOS SOCIALES'!N154 -> Promedio
B32: 174 | C32: ='DIAGNOSTICO ASPECTOS SOCIALES'!N161 -> Promedio
B33: 175 | C33: ='DIAGNOSTICO ASPECTOS SOCIALES'!N168 -> Promedio
B34: 176 | C34: ='DIAGNOSTICO ASPECTOS SOCIALES'!N175 -> Promedio
B36: E5. Social Interno (Se hace mediante encuesta a la cadena de producción de la empresa)
B37: 177 | C37: ='DIAGNOSTICO ASPECTOS SOCIALES'!N184 -> Promedio
B38: 178 | C38: ='DIAGNOSTICO ASPECTOS SOCIALES'!N191 -> Promedio
B39: 179 | C39: ='DIAGNOSTICO ASPECTOS SOCIALES'!N198 -> Promedio
B40: 180 | C40: ='DIAGNOSTICO ASPECTOS SOCIALES'!N205 -> Promedio
B41: 181 | C41: ='DIAGNOSTICO ASPECTOS SOCIALES'!N212 -> Promedio
B42: 182 | C42: ='DIAGNOSTICO ASPECTOS SOCIALES'!N219 -> Promedio
B43: 186 | C43: ='DIAGNOSTICO ASPECTOS SOCIALES'!N226 -> Promedio
B44: 184 | C44: ='DIAGNOSTICO ASPECTOS SOCIALES'!N233 -> Promedio
B45: 185 | C45: ='DIAGNOSTICO ASPECTOS SOCIALES'!N240 -> Promedio
B46: 186 | C46: ='DIAGNOSTICO ASPECTOS SOCIALES'!N247 -> Promedio
B47: 187 | C47: ='DIAGNOSTICO ASPECTOS SOCIALES'!N254 -> Promedio
B48: 188 | C48: ='DIAGNOSTICO ASPECTOS SOCIALES'!N261 -> Promedio
B50: E6. Social Externo (Se hace mediante encuesta de producción y servicio de los clientes)
B51: 189 | C51: ='DIAGNOSTICO ASPECTOS SOCIALES'!N271 -> Promedio
B52: 190 | C52: ='DIAGNOSTICO ASPECTOS SOCIALES'!N278 -> Promedio
B53: 191 | C53: ='DIAGNOSTICO ASPECTOS SOCIALES'!N285 -> Promedio
B54: 192 | C54: ='DIAGNOSTICO ASPECTOS SOCIALES'!N292 -> Promedio
B55: 193 | C55: ='DIAGNOSTICO ASPECTOS SOCIALES'!N299 -> Promedio
B56: 194 | C56: ='DIAGNOSTICO ASPECTOS SOCIALES'!N306 -> Promedio

Sheet DIAGNOSTICO ALMACEN
B2: Aspectos ambientales
B4: F. Almacenamiento e insumo de materia prima
E5: 3 | G5: 2 | I5: 1 | K5: 0
B7: F1. Registro y fichas de almacenamiento de los insumos y productos
B9: 195.- | C9: ¿Requiere de articulos y/o materias primas?
F11: IMP | H11: M | J11: AC | L11: NA | M11: =IF(E11="X","",IF(G11="X","",IF(I11="X","",IF(K11="X","","Elegir opción")))) -> Elegir opción | N11: =IF(E11="X",3,IF(G11="X",2,IF(I11="X",1,IF(K11="X",0,"Promedio")))) -> Promedio
B16: 196.- | C16: ¿Clasifica los insumos y materia prima que almacena? (Según su composición química, física, peligrosidad etc.)
F18: IMP | H18: M | J18: AC | L18: NA | M18: =IF(E18="X","",IF(G18="X","",IF(I18="X","",IF(K18="X","","Elegir opción")))) -> Elegir opción | N18: =IF(E18="X",3,IF(G18="X",2,IF(I18="X",1,IF(K18="X",0,"Promedio")))) -> Promedio
B23: 197.- | C23: ¿Dispone del espacio suficiente y adecuado para almacenar la materia prima e insumos que se necesita.
F25: IMP | H25: M | J25: AC | L25: NA | M25: =IF(E25="X","",IF(G25="X","",IF(I25="X","",IF(K25="X","","Elegir opción")))) -> Elegir opción | N25: =IF(E25="X",3,IF(G25="X",2,IF(I25="X",1,IF(K25="X",0,"Promedio")))) -> Promedio
B30: 198.- | C30: ¿Dispone los insumos y materia prima peligrosa según alguna norma?
F32: IMP | H32: M | J32: AC | L32: NA | M32: =IF(E32="X","",IF(G32="X","",IF(I32="X","",IF(K32="X","","Elegir opción")))) -> Elegir opción | N32: =IF(E32="X",3,IF(G32="X",2,IF(I32="X",1,IF(K32="X",0,"Promedio")))) -> Promedio
B37: 199.- | C37: ¿Utiliza estrategias para la compra de materiales renovables, reutilizables y reciclables?
F39: IMP | H39: M | J39: AC | L39: NA | M39: =IF(E39="X","",IF(G39="X","",IF(I39="X","",IF(K39="X","","Elegir opción")))) -> Elegir opción | N39: =IF(E39="X",3,IF(G39="X",2,IF(I39="X",1,IF(K39="X",0,"Promedio")))) -> Promedio
B44: 200.- | C44: ¿Considera que el área es adecuada para el almacenamiento de los diferentes artículos que maneja?
F46: IMP | H46: M | J46: AC | L46: NA | M46: =IF(E46="X","",IF(G46="X","",IF(I46="X","",IF(K46="X","","Elegir opción")))) -> Elegir opción | N46: =IF(E46="X",3,IF(G46="X",2,IF(I46="X",1,IF(K46="X",0,"Promedio")))) -> Promedio
B51: 201.- | C51: ¿Se presentan impactos ambientales en la bodega?
F53: IMP | H53: M | J53: AC | L53: NA | M53: =IF(E53="X","",IF(G53="X","",IF(I53="X","",IF(K53="X","","Elegir opción")))) -> Elegir opción | N53: =IF(E53="X",3,IF(G53="X",2,IF(I53="X",1,IF(K53="X",0,"Promedio")))) -> Promedio
B58: 202.- | C58: ¿Cuenta con las fichas técnicas de todos los productos peligrosos que se requieren para el desarrollo de las actividades?
F60: IMP | H60: M | J60: AC | L60: NA | M60: =IF(E60="X","",IF(G60="X","",IF(I60="X","",IF(K60="X","","Elegir opción")))) -> Elegir opción | N60: =IF(E60="X",3,IF(G60="X",2,IF(I60="X",1,IF(K60="X",0,"Promedio")))) -> Promedio
B66: F2. Señalización y rutas de almacenamiento
B68: 203.- | C68: El área de almacén de la empresa se encuentra señalizada de acuerda a la normatividad?
F70: IMP | H70: M | J70: AC | L70: NA | M70: =IF(E70="X","",IF(G70="X","",IF(I70="X","",IF(K70="X","","Elegir opción")))) -> Elegir opción | N70: =IF(E70="X",3,IF(G70="X",2,IF(I70="X",1,IF(K70="X",0,"Promedio")))) -> Promedio
B75: 204.- | C75: El almacén se encuentra con iluminación adecuada.
F77: IMP | H77: M | J77: AC | L77: NA | M77: =IF(E77="X","",IF(G77="X","",IF(I77="X","",IF(K77="X","","Elegir opción")))) -> Elegir opción | N77: =IF(E77="X",3,IF(G77="X",2,IF(I77="X",1,IF(K77="X",0,"Promedio")))) -> Promedio
B82: 205.- | C82: En caso de emergencia existen extintores adecuados de acuerdo a los insumos almacenados.
F84: IMP | H84: M | J84: AC | L84: NA | M84: =IF(E84="X","",IF(G84="X","",IF(I84="X","",IF(K84="X","","Elegir opción")))) -> Elegir opción | N84: =IF(E84="X",3,IF(G84="X",2,IF(I84="X",1,IF(K84="X",0,"Promedio")))) -> Promedio
B89: F3. Insumos con alto riesgo de peligrosidad
B91: 206.- | C91: Los insumos y materia prima tiene los pictogramas de acuerdo a las sustancias almacenadas.
F93: IMP | H93: M | J93: AC | L93: NA | M93: =IF(E93="X","",IF(G93="X","",IF(I93="X","",IF(K93="X","","Elegir opción")))) -> Elegir opción | N93: =IF(E93="X",3,IF(G93="X",2,IF(I93="X",1,IF(K93="X",0,"Promedio")))) -> Promedio
B98: 207.- | C98: Los pictogramas son de acuerdo a las sustancias almacenadas.
F100: IMP | H100: M | J100: AC | L100: NA | M100: =IF(E100="X","",IF(G100="X","",IF(I100="X","",IF(K100="X","","Elegir opción")))) -> Elegir opción | N100: =IF(E100="X",3,IF(G100="X",2,IF(I100="X",1,IF(K100="X",0,"Promedio")))) -> Promedio
B105: 208.- | C105: El personal encargado de almacén mantiene los sistemas de alerta.
F107: IMP | H107: M | J107: AC | L107: NA | M107: =IF(E107="X","",IF(G107="X","",IF(I107="X","",IF(K107="X","","Elegir opción")))) -> Elegir opción | N107: =IF(E107="X",3,IF(G107="X",2,IF(I107="X",1,IF(K107="X",0,"Promedio")))) -> Promedio
B112: 209.- | C112: Se han realizado simulacros de evacuación en caso de emergencia y/o evacuación por derrames de sustancias.
F114: IMP | H114: M | J114: AC | L114: NA | M114: =IF(E114="X","",IF(G114="X","",IF(I114="X","",IF(K114="X","","Elegir opción")))) -> Elegir opción | N114: =IF(E114="X",3,IF(G114="X",2,IF(I114="X",1,IF(K114="X",0,"Promedio")))) -> Promedio
B119: 210.- | C119: El encargado de almacén conoce los listados y pictogramas con la nomenclatura correspondiente de identificación de sustancias peligrosas.
F121: IMP | H121: M | J121: AC | L121: NA | M121: =IF(E121="X","",IF(G121="X","",IF(I121="X","",IF(K121="X","","Elegir opción")))) -> Elegir opción | N121: =IF(E121="X",3,IF(G121="X",2,IF(I121="X",1,IF(K121="X",0,"Promedio")))) -> Promedio

Sheet DATOS F.
B2: Diagnóstico almacén
B4: F1. Registro y y fichas de almacenamiento de los insumos y productos
B5: Item | C5: Diagnóstico promedial
B6: 195 | C6: ='DIAGNOSTICO ALMACEN'!N11 -> Promedio
B7: 196 | C7: ='DIAGNOSTICO ALMACEN'!N18 -> Promedio | G7: F1 | H7: =SUMIF(C6:C13,">0",C6:C13)/COUNTIF(C6:C13,">0") -> #DIV/0!
B8: 197 | C8: ='DIAGNOSTICO ALMACEN'!N25 -> Promedio | G8: F2 | H8: =SUMIF(C16:C18,">0",C16:C18)/COUNTIF(C16:C18,">0") -> #DIV/0!
B9: 198 | C9: ='DIAGNOSTICO ALMACEN'!N32 -> Promedio | G9: F3 | H9: =SUMIF(C21:C25,">0",C21:C25)/COUNTIF(C21:C25,">0") -> #DIV/0!
B10: 199 | C10: ='DIAGNOSTICO ALMACEN'!N39 -> Promedio
B11: 200 | C11: ='DIAGNOSTICO ALMACEN'!N46 -> Promedio | G11: Diagnóstico almacén | H11: =((SUM(H7:H10)/3)*100)/3 -> #DIV/0!
B12: 201 | C12: ='DIAGNOSTICO ALMACEN'!N53 -> Promedio
B13: 202 | C13: ='DIAGNOSTICO ALMACEN'!N60 -> Promedio
B15: F2. Señalización y rutas de almacenamiento
B16: 203 | C16: ='DIAGNOSTICO ALMACEN'!N70 -> Promedio
B17: 204 | C17: ='DIAGNOSTICO ALMACEN'!N77 -> Promedio
B18: 205 | C18: ='DIAGNOSTICO ALMACEN'!N84 -> Promedio
B20: F3. Insumos con alto riesgo de peligrosidad
B21: 206 | C21: ='DIAGNOSTICO ALMACEN'!N93 -> Promedio
B22: 207 | C22: ='DIAGNOSTICO ALMACEN'!N100 -> Promedio
B23: 208 | C23: ='DIAGNOSTICO ALMACEN'!N107 -> Promedio
B24: 209 | C24: ='DIAGNOSTICO ALMACEN'!N114 -> Promedio
B25: 210 | C25: ='DIAGNOSTICO ALMACEN'!N121 -> Promedio

Sheet PROMEDIO PORCENTUAL DIAGNOSTICO
B2: Promedio porcentual diagnóstico
B3: A | C3: Diagnóstico económico | D3: ='DATOS A.'!H26 -> #DIV/0!
B4: B | C4: Diagnóstico ambiental | D4: ='DATOS B.'!H17 -> #DIV/0!
B5: C | C5: Diagnóstico energía | D5: ='DATOS C.'!H11 -> #DIV/0!
B6: D | C6: Diagnóstico seguridad y salud en el trabajo | D6: ='DATOS D.'!G19 -> #DIV/0!
B7: E | C7: Diagnóstico aspectos sociales | D7: ='DATOS E.'!J16 -> #DIV/0!
B8: F | C8: Diagnóstico almacén | D8: ='DATOS F.'!H11 -> #DIV/0!
